{"_ts":[1509552302,1509725028,1509811341,1509897710],"_r":{"breakdown":{"html":{"bytes":[55294,54980,54798,54958],"requests":[11,11,11,11]},"js":{"bytes":[397147,398042,397700,398075],"requests":[18,17,18,18]},"css":{"bytes":[74629,74629,74629,74629],"requests":[2,2,2,2]},"image":{"bytes":[624122,624020,624072,623972],"requests":[21,22,21,21]},"flash":{"bytes":[0,0,0,0],"requests":[0,0,0,0]},"font":{"bytes":[1196997,1196898,1197108,1196886],"requests":[46,46,46,46]},"video":{"bytes":[0,0,0,0],"requests":[0,0,0,0]},"other":{"bytes":[6649,7509,7541,7530],"requests":[4,4,4,4]}},"date":[1509552302,1509725028,1509811341,1509897710],"domElements":[1831,1831,1833,1831],"domInteractive":[2257,2593,2466,2145],"firstPaint":[1422,1637,1541,1408],"fullyLoaded":[6677,7537,7616,7453],"id":["171101_M9_acb7f4603107b8760fe7f14c5a6467eb","171103_8M_929f7aab4e5994fec150aa2b6d68d3b8","171104_SA_01708991db07bf06b53a0cc30bb7e682","171105_J5_0f317062ca91436e9217b2bd95ebb6bf"],"loadTime":[3789,6678,4228,4060],"render":[1468,1902,1585,1471],"SpeedIndex":[4536,4827,5019,5120],"TTFB":[747,825,773,665],"videoFrames":[[{"_i":"frame_0000.jpg","_t":0,"_vc":0},{"_i":"frame_0015.jpg","_t":1500,"_vc":10},{"_i":"frame_0017.jpg","_t":1700,"_vc":20},{"_i":"frame_0018.jpg","_t":1800,"_vc":21},{"_i":"frame_0021.jpg","_t":2100,"_vc":25},{"_i":"frame_0025.jpg","_t":2500,"_vc":24},{"_i":"frame_0028.jpg","_t":2800,"_vc":29},{"_i":"frame_0031.jpg","_t":3100,"_vc":29},{"_i":"frame_0033.jpg","_t":3300,"_vc":29},{"_i":"frame_0035.jpg","_t":3500,"_vc":29},{"_i":"frame_0037.jpg","_t":3700,"_vc":29},{"_i":"frame_0050.jpg","_t":5000,"_vc":55},{"_i":"frame_0051.jpg","_t":5100,"_vc":55},{"_i":"frame_0053.jpg","_t":5300,"_vc":55},{"_i":"frame_0056.jpg","_t":5600,"_vc":55},{"_i":"frame_0057.jpg","_t":5700,"_vc":55},{"_i":"frame_0059.jpg","_t":5900,"_vc":94},{"_i":"frame_0061.jpg","_t":6100,"_vc":94},{"_i":"frame_0063.jpg","_t":6300,"_vc":95},{"_i":"frame_0064.jpg","_t":6400,"_vc":95},{"_i":"frame_0066.jpg","_t":6600,"_vc":95},{"_i":"frame_0067.jpg","_t":6700,"_vc":100},{"_i":"frame_0069.jpg","_t":6900,"_vc":100},{"_i":"frame_0071.jpg","_t":7100,"_vc":100},{"_i":"frame_0073.jpg","_t":7300,"_vc":100},{"_i":"frame_0075.jpg","_t":7500,"_vc":100},{"_i":"frame_0076.jpg","_t":7600,"_vc":100},{"_i":"frame_0078.jpg","_t":7800,"_vc":100},{"_i":"frame_0080.jpg","_t":8000,"_vc":100},{"_i":"frame_0081.jpg","_t":8100,"_vc":100},{"_i":"frame_0083.jpg","_t":8300,"_vc":100},{"_i":"frame_0084.jpg","_t":8400,"_vc":100},{"_i":"frame_0085.jpg","_t":8500,"_vc":100},{"_i":"frame_0086.jpg","_t":8600,"_vc":100},{"_i":"frame_0087.jpg","_t":8700,"_vc":100},{"_i":"frame_0088.jpg","_t":8800,"_vc":100}],[{"_i":"frame_0000.jpg","_t":0,"_vc":0},{"_i":"frame_0019.jpg","_t":1900,"_vc":10},{"_i":"frame_0021.jpg","_t":2100,"_vc":16},{"_i":"frame_0024.jpg","_t":2400,"_vc":25},{"_i":"frame_0029.jpg","_t":2900,"_vc":29},{"_i":"frame_0032.jpg","_t":3200,"_vc":29},{"_i":"frame_0036.jpg","_t":3600,"_vc":29},{"_i":"frame_0039.jpg","_t":3900,"_vc":29},{"_i":"frame_0041.jpg","_t":4100,"_vc":29},{"_i":"frame_0051.jpg","_t":5100,"_vc":55},{"_i":"frame_0054.jpg","_t":5400,"_vc":55},{"_i":"frame_0055.jpg","_t":5500,"_vc":55},{"_i":"frame_0057.jpg","_t":5700,"_vc":55},{"_i":"frame_0059.jpg","_t":5900,"_vc":55},{"_i":"frame_0060.jpg","_t":6000,"_vc":55},{"_i":"frame_0062.jpg","_t":6200,"_vc":94},{"_i":"frame_0065.jpg","_t":6500,"_vc":94},{"_i":"frame_0066.jpg","_t":6600,"_vc":94},{"_i":"frame_0068.jpg","_t":6800,"_vc":95},{"_i":"frame_0069.jpg","_t":6900,"_vc":95},{"_i":"frame_0071.jpg","_t":7100,"_vc":94},{"_i":"frame_0072.jpg","_t":7200,"_vc":94},{"_i":"frame_0073.jpg","_t":7300,"_vc":100},{"_i":"frame_0074.jpg","_t":7400,"_vc":100},{"_i":"frame_0075.jpg","_t":7500,"_vc":100},{"_i":"frame_0077.jpg","_t":7700,"_vc":100},{"_i":"frame_0079.jpg","_t":7900,"_vc":100},{"_i":"frame_0080.jpg","_t":8000,"_vc":100},{"_i":"frame_0082.jpg","_t":8200,"_vc":100},{"_i":"frame_0083.jpg","_t":8300,"_vc":100},{"_i":"frame_0085.jpg","_t":8500,"_vc":100},{"_i":"frame_0087.jpg","_t":8700,"_vc":100},{"_i":"frame_0089.jpg","_t":8900,"_vc":100},{"_i":"frame_0091.jpg","_t":9100,"_vc":100},{"_i":"frame_0093.jpg","_t":9300,"_vc":100},{"_i":"frame_0094.jpg","_t":9400,"_vc":100},{"_i":"frame_0096.jpg","_t":9600,"_vc":100}],[{"_i":"frame_0000.jpg","_t":0,"_vc":0},{"_i":"frame_0016.jpg","_t":1600,"_vc":10},{"_i":"frame_0020.jpg","_t":2000,"_vc":24},{"_i":"frame_0022.jpg","_t":2200,"_vc":29},{"_i":"frame_0029.jpg","_t":2900,"_vc":29},{"_i":"frame_0035.jpg","_t":3500,"_vc":29},{"_i":"frame_0040.jpg","_t":4000,"_vc":29},{"_i":"frame_0043.jpg","_t":4300,"_vc":29},{"_i":"frame_0045.jpg","_t":4500,"_vc":29},{"_i":"frame_0057.jpg","_t":5700,"_vc":55},{"_i":"frame_0059.jpg","_t":5900,"_vc":55},{"_i":"frame_0061.jpg","_t":6100,"_vc":55},{"_i":"frame_0063.jpg","_t":6300,"_vc":55},{"_i":"frame_0065.jpg","_t":6500,"_vc":94},{"_i":"frame_0067.jpg","_t":6700,"_vc":94},{"_i":"frame_0069.jpg","_t":6900,"_vc":94},{"_i":"frame_0071.jpg","_t":7100,"_vc":95},{"_i":"frame_0073.jpg","_t":7300,"_vc":95},{"_i":"frame_0075.jpg","_t":7500,"_vc":94},{"_i":"frame_0076.jpg","_t":7600,"_vc":100},{"_i":"frame_0078.jpg","_t":7800,"_vc":100},{"_i":"frame_0079.jpg","_t":7900,"_vc":100},{"_i":"frame_0081.jpg","_t":8100,"_vc":100},{"_i":"frame_0082.jpg","_t":8200,"_vc":100},{"_i":"frame_0084.jpg","_t":8400,"_vc":100},{"_i":"frame_0085.jpg","_t":8500,"_vc":100},{"_i":"frame_0086.jpg","_t":8600,"_vc":100},{"_i":"frame_0088.jpg","_t":8800,"_vc":100},{"_i":"frame_0089.jpg","_t":8900,"_vc":100},{"_i":"frame_0091.jpg","_t":9100,"_vc":100},{"_i":"frame_0093.jpg","_t":9300,"_vc":100},{"_i":"frame_0094.jpg","_t":9400,"_vc":100},{"_i":"frame_0096.jpg","_t":9600,"_vc":100},{"_i":"frame_0097.jpg","_t":9700,"_vc":100},{"_i":"frame_0098.jpg","_t":9800,"_vc":100}],[{"_i":"frame_0000.jpg","_t":0,"_vc":0},{"_i":"frame_0015.jpg","_t":1500,"_vc":10},{"_i":"frame_0018.jpg","_t":1800,"_vc":16},{"_i":"frame_0020.jpg","_t":2000,"_vc":24},{"_i":"frame_0024.jpg","_t":2400,"_vc":24},{"_i":"frame_0029.jpg","_t":2900,"_vc":29},{"_i":"frame_0033.jpg","_t":3300,"_vc":29},{"_i":"frame_0038.jpg","_t":3800,"_vc":29},{"_i":"frame_0040.jpg","_t":4000,"_vc":29},{"_i":"frame_0041.jpg","_t":4100,"_vc":29},{"_i":"frame_0056.jpg","_t":5600,"_vc":55},{"_i":"frame_0058.jpg","_t":5800,"_vc":55},{"_i":"frame_0060.jpg","_t":6000,"_vc":55},{"_i":"frame_0062.jpg","_t":6200,"_vc":55},{"_i":"frame_0066.jpg","_t":6600,"_vc":55},{"_i":"frame_0068.jpg","_t":6800,"_vc":94},{"_i":"frame_0070.jpg","_t":7000,"_vc":94},{"_i":"frame_0071.jpg","_t":7100,"_vc":94},{"_i":"frame_0072.jpg","_t":7200,"_vc":94},{"_i":"frame_0074.jpg","_t":7400,"_vc":95},{"_i":"frame_0075.jpg","_t":7500,"_vc":100},{"_i":"frame_0076.jpg","_t":7600,"_vc":100},{"_i":"frame_0078.jpg","_t":7800,"_vc":100},{"_i":"frame_0080.jpg","_t":8000,"_vc":100},{"_i":"frame_0082.jpg","_t":8200,"_vc":100},{"_i":"frame_0084.jpg","_t":8400,"_vc":100},{"_i":"frame_0085.jpg","_t":8500,"_vc":100},{"_i":"frame_0086.jpg","_t":8600,"_vc":100},{"_i":"frame_0087.jpg","_t":8700,"_vc":100},{"_i":"frame_0089.jpg","_t":8900,"_vc":100},{"_i":"frame_0091.jpg","_t":9100,"_vc":100},{"_i":"frame_0092.jpg","_t":9200,"_vc":100},{"_i":"frame_0094.jpg","_t":9400,"_vc":100},{"_i":"frame_0095.jpg","_t":9500,"_vc":100},{"_i":"frame_0096.jpg","_t":9600,"_vc":100}]],"visualComplete":[6700,7300,7600,7500],"lighthouse":[null,null,null,null],"pagespeed":[84,85,84,84]}}