{"_ts":[1564794363,1565053448,1565226364,1565312615,1565744630,1565831023],"_r":{"breakdown":{"html":{"bytes":[77331,77649,77287,77271,77549,77243],"requests":[16,16,16,16,16,16]},"js":{"bytes":[557093,557087,557880,558073,559064,559086],"requests":[23,23,23,23,23,23]},"css":{"bytes":[63497,63497,63566,63566,63566,63566],"requests":[2,2,2,2,2,2]},"image":{"bytes":[460373,808624,460373,456154,808852,460373],"requests":[28,30,28,28,30,28]},"flash":{"bytes":[0,0,0,0,0,0],"requests":[0,0,0,0,0,0]},"font":{"bytes":[634592,634592,634592,634592,634592,634592],"requests":[25,25,25,25,25,25]},"video":{"bytes":[0,0,0,0,0,0],"requests":[0,0,0,0,0,0]},"other":{"bytes":[1829,1828,2089,2130,2090,2093],"requests":[10,11,11,12,10,11]}},"date":[1564794363,1565053448,1565226364,1565312615,1565744630,1565831023],"domElements":[5079,5126,5073,5073,5114,5067],"domInteractive":[3142,4152,3596,4116,4351,4404],"firstPaint":[2332.4350000003,2666.5750000002,2496.3699999935,3021.4449999912,3439.9299999932,3477.7199999953],"fullyLoaded":[10327,11945,10609,12015,11995,12808],"id":["190803_27_f6dd09e85392e49985edf2e40cc86fe4","190806_03_118352aa78aaadf36ac41125098456fe","190808_1H_546f3b35515de63fc7fb462d96d1d88f","190809_E0_b3ce177b17544b83cc3549e5d9a29991","190814_B2_2e31cd62bbae3cf3859f4f51dcd0e7a4","190815_VA_7af536c8285f853fac28f5bfd051c289"],"loadTime":[8225,4,8481,9955,9892,10889],"render":[2300,2700,2500,3100,3400,3500],"SpeedIndex":[3232,3812,3369,4101,4381,4464],"TTFB":[1134,1181,1212,1549,2027,2207],"videoFrames":[[{"_i":"ms_000000.jpg","_t":0,"_vc":0},{"_i":"ms_002300.jpg","_t":2300,"_vc":73},{"_i":"ms_002700.jpg","_t":2700,"_vc":74},{"_i":"ms_003100.jpg","_t":3100,"_vc":74},{"_i":"ms_004100.jpg","_t":4100,"_vc":75},{"_i":"ms_004500.jpg","_t":4500,"_vc":75},{"_i":"ms_005100.jpg","_t":5100,"_vc":87},{"_i":"ms_005800.jpg","_t":5800,"_vc":85},{"_i":"ms_005900.jpg","_t":5900,"_vc":92},{"_i":"ms_006700.jpg","_t":6700,"_vc":92},{"_i":"ms_006900.jpg","_t":6900,"_vc":92},{"_i":"ms_007200.jpg","_t":7200,"_vc":100}],[{"_i":"ms_000000.jpg","_t":0,"_vc":0},{"_i":"ms_002700.jpg","_t":2700,"_vc":73},{"_i":"ms_003200.jpg","_t":3200,"_vc":74},{"_i":"ms_003800.jpg","_t":3800,"_vc":74},{"_i":"ms_004100.jpg","_t":4100,"_vc":75},{"_i":"ms_005000.jpg","_t":5000,"_vc":75},{"_i":"ms_005100.jpg","_t":5100,"_vc":75},{"_i":"ms_005200.jpg","_t":5200,"_vc":75},{"_i":"ms_005300.jpg","_t":5300,"_vc":76},{"_i":"ms_005800.jpg","_t":5800,"_vc":76},{"_i":"ms_005900.jpg","_t":5900,"_vc":76},{"_i":"ms_006000.jpg","_t":6000,"_vc":75},{"_i":"ms_006300.jpg","_t":6300,"_vc":92},{"_i":"ms_006500.jpg","_t":6500,"_vc":92},{"_i":"ms_007100.jpg","_t":7100,"_vc":92},{"_i":"ms_008200.jpg","_t":8200,"_vc":92},{"_i":"ms_008800.jpg","_t":8800,"_vc":100}],[{"_i":"ms_000000.jpg","_t":0,"_vc":0},{"_i":"ms_002500.jpg","_t":2500,"_vc":73},{"_i":"ms_002900.jpg","_t":2900,"_vc":75},{"_i":"ms_003200.jpg","_t":3200,"_vc":75},{"_i":"ms_003500.jpg","_t":3500,"_vc":75},{"_i":"ms_003600.jpg","_t":3600,"_vc":75},{"_i":"ms_003700.jpg","_t":3700,"_vc":74},{"_i":"ms_004100.jpg","_t":4100,"_vc":75},{"_i":"ms_004200.jpg","_t":4200,"_vc":76},{"_i":"ms_004600.jpg","_t":4600,"_vc":76},{"_i":"ms_004700.jpg","_t":4700,"_vc":76},{"_i":"ms_004800.jpg","_t":4800,"_vc":75},{"_i":"ms_004900.jpg","_t":4900,"_vc":76},{"_i":"ms_005100.jpg","_t":5100,"_vc":84},{"_i":"ms_005400.jpg","_t":5400,"_vc":84},{"_i":"ms_005600.jpg","_t":5600,"_vc":92},{"_i":"ms_006000.jpg","_t":6000,"_vc":92},{"_i":"ms_006100.jpg","_t":6100,"_vc":92},{"_i":"ms_006900.jpg","_t":6900,"_vc":92},{"_i":"ms_007000.jpg","_t":7000,"_vc":93},{"_i":"ms_007100.jpg","_t":7100,"_vc":92},{"_i":"ms_007300.jpg","_t":7300,"_vc":100}],[{"_i":"ms_000000.jpg","_t":0,"_vc":0},{"_i":"ms_003100.jpg","_t":3100,"_vc":74},{"_i":"ms_003700.jpg","_t":3700,"_vc":74},{"_i":"ms_003900.jpg","_t":3900,"_vc":76},{"_i":"ms_004900.jpg","_t":4900,"_vc":75},{"_i":"ms_005000.jpg","_t":5000,"_vc":76},{"_i":"ms_005100.jpg","_t":5100,"_vc":74},{"_i":"ms_005400.jpg","_t":5400,"_vc":75},{"_i":"ms_005600.jpg","_t":5600,"_vc":76},{"_i":"ms_006100.jpg","_t":6100,"_vc":85},{"_i":"ms_006200.jpg","_t":6200,"_vc":87},{"_i":"ms_006300.jpg","_t":6300,"_vc":87},{"_i":"ms_006400.jpg","_t":6400,"_vc":85},{"_i":"ms_006500.jpg","_t":6500,"_vc":92},{"_i":"ms_006700.jpg","_t":6700,"_vc":92},{"_i":"ms_006900.jpg","_t":6900,"_vc":92},{"_i":"ms_007400.jpg","_t":7400,"_vc":92},{"_i":"ms_007500.jpg","_t":7500,"_vc":92},{"_i":"ms_009000.jpg","_t":9000,"_vc":100}],[{"_i":"ms_000000.jpg","_t":0,"_vc":0},{"_i":"ms_003400.jpg","_t":3400,"_vc":60},{"_i":"ms_003500.jpg","_t":3500,"_vc":73},{"_i":"ms_003900.jpg","_t":3900,"_vc":74},{"_i":"ms_004800.jpg","_t":4800,"_vc":75},{"_i":"ms_005100.jpg","_t":5100,"_vc":75},{"_i":"ms_005300.jpg","_t":5300,"_vc":76},{"_i":"ms_006200.jpg","_t":6200,"_vc":76},{"_i":"ms_006400.jpg","_t":6400,"_vc":76},{"_i":"ms_006500.jpg","_t":6500,"_vc":91},{"_i":"ms_006900.jpg","_t":6900,"_vc":92},{"_i":"ms_007000.jpg","_t":7000,"_vc":92},{"_i":"ms_007100.jpg","_t":7100,"_vc":93},{"_i":"ms_007300.jpg","_t":7300,"_vc":92},{"_i":"ms_007400.jpg","_t":7400,"_vc":92},{"_i":"ms_007900.jpg","_t":7900,"_vc":92},{"_i":"ms_008000.jpg","_t":8000,"_vc":92},{"_i":"ms_008300.jpg","_t":8300,"_vc":92},{"_i":"ms_008500.jpg","_t":8500,"_vc":92},{"_i":"ms_008800.jpg","_t":8800,"_vc":100}],[{"_i":"ms_000000.jpg","_t":0,"_vc":0},{"_i":"ms_003500.jpg","_t":3500,"_vc":74},{"_i":"ms_003900.jpg","_t":3900,"_vc":75},{"_i":"ms_004300.jpg","_t":4300,"_vc":75},{"_i":"ms_004500.jpg","_t":4500,"_vc":76},{"_i":"ms_004800.jpg","_t":4800,"_vc":74},{"_i":"ms_005700.jpg","_t":5700,"_vc":76},{"_i":"ms_006200.jpg","_t":6200,"_vc":76},{"_i":"ms_006300.jpg","_t":6300,"_vc":76},{"_i":"ms_006600.jpg","_t":6600,"_vc":91},{"_i":"ms_007000.jpg","_t":7000,"_vc":92},{"_i":"ms_007500.jpg","_t":7500,"_vc":92},{"_i":"ms_008400.jpg","_t":8400,"_vc":92},{"_i":"ms_008500.jpg","_t":8500,"_vc":92},{"_i":"ms_008900.jpg","_t":8900,"_vc":100}]],"visualComplete":[7200,8800,7300,9000,8800,8900],"lighthouse":[35,35,35,35,35,35],"pagespeed":[68,64,68,68,64,68]}}