{"_ts":[1535792613,1535879027,1536051891],"_r":{"breakdown":{"html":{"bytes":[33048,33021,33052],"requests":[15,15,15]},"js":{"bytes":[497690,497141,497575],"requests":[24,24,24]},"css":{"bytes":[49152,49153,49152],"requests":[2,2,2]},"image":{"bytes":[915244,915226,915151],"requests":[49,49,49]},"flash":{"bytes":[0,0,0],"requests":[0,0,0]},"font":{"bytes":[627592,616768,639044],"requests":[25,23,25]},"video":{"bytes":[0,0,0],"requests":[0,0,0]},"other":{"bytes":[3803,3811,3809],"requests":[8,8,8]}},"date":[1535792613,1535879027,1536051891],"domElements":[1946,1945,1945],"domInteractive":[2047,2234,1924],"firstPaint":[1607.4999999983,1746.8000000008,1653.8],"fullyLoaded":[8048,8188,8131],"id":["180901_6P_462726a80ae1b6fdc5213f910b36777d","180902_FB_5c4280f8ae5ce217b35764bbd2597611","180904_AH_2f17cc7f4aa4ee789a16c87b7ef37474"],"loadTime":[3901,4160,3886],"render":[1700,1800,1700],"SpeedIndex":[2071,3775,2026],"TTFB":[696,1070,905],"videoFrames":[[{"_i":"ms_000000.jpg","_t":0,"_vc":0},{"_i":"ms_001700.jpg","_t":1700,"_vc":8},{"_i":"ms_001900.jpg","_t":1900,"_vc":65},{"_i":"ms_002000.jpg","_t":2000,"_vc":87},{"_i":"ms_002100.jpg","_t":2100,"_vc":87},{"_i":"ms_002200.jpg","_t":2200,"_vc":87},{"_i":"ms_002300.jpg","_t":2300,"_vc":94},{"_i":"ms_002600.jpg","_t":2600,"_vc":95},{"_i":"ms_003300.jpg","_t":3300,"_vc":95},{"_i":"ms_003800.jpg","_t":3800,"_vc":95},{"_i":"ms_004300.jpg","_t":4300,"_vc":95},{"_i":"ms_004500.jpg","_t":4500,"_vc":100}],[{"_i":"ms_000000.jpg","_t":0,"_vc":0},{"_i":"ms_001800.jpg","_t":1800,"_vc":9},{"_i":"ms_002000.jpg","_t":2000,"_vc":9},{"_i":"ms_002100.jpg","_t":2100,"_vc":9},{"_i":"ms_002200.jpg","_t":2200,"_vc":8},{"_i":"ms_002300.jpg","_t":2300,"_vc":9},{"_i":"ms_002700.jpg","_t":2700,"_vc":21},{"_i":"ms_002800.jpg","_t":2800,"_vc":20},{"_i":"ms_002900.jpg","_t":2900,"_vc":19},{"_i":"ms_003000.jpg","_t":3000,"_vc":21},{"_i":"ms_003600.jpg","_t":3600,"_vc":20},{"_i":"ms_003700.jpg","_t":3700,"_vc":19},{"_i":"ms_004100.jpg","_t":4100,"_vc":95},{"_i":"ms_004800.jpg","_t":4800,"_vc":98},{"_i":"ms_004900.jpg","_t":4900,"_vc":100}],[{"_i":"ms_000000.jpg","_t":0,"_vc":0},{"_i":"ms_001700.jpg","_t":1700,"_vc":67},{"_i":"ms_001800.jpg","_t":1800,"_vc":67},{"_i":"ms_001900.jpg","_t":1900,"_vc":65},{"_i":"ms_002000.jpg","_t":2000,"_vc":65},{"_i":"ms_002200.jpg","_t":2200,"_vc":87},{"_i":"ms_002300.jpg","_t":2300,"_vc":88},{"_i":"ms_002600.jpg","_t":2600,"_vc":89},{"_i":"ms_002700.jpg","_t":2700,"_vc":95},{"_i":"ms_002800.jpg","_t":2800,"_vc":95},{"_i":"ms_002900.jpg","_t":2900,"_vc":95},{"_i":"ms_003000.jpg","_t":3000,"_vc":95},{"_i":"ms_003700.jpg","_t":3700,"_vc":95},{"_i":"ms_003800.jpg","_t":3800,"_vc":95},{"_i":"ms_004600.jpg","_t":4600,"_vc":100}]],"visualComplete":[4500,4900,4600],"lighthouse":[35,35,35],"pagespeed":[70,69,70]}}