{"_ts":[1517563553,1517648692,1517735278,1517821390],"_r":{"breakdown":{"html":{"bytes":[62554,63467,64086,63473],"requests":[17,18,19,18]},"js":{"bytes":[348533,371484,371615,360774],"requests":[17,17,17,17]},"css":{"bytes":[61227,45671,58360,62935],"requests":[3,3,3,3]},"image":{"bytes":[330427,277780,300591,315515],"requests":[28,28,28,28]},"flash":{"bytes":[0,0,0,0],"requests":[0,0,0,0]},"font":{"bytes":[189769,204775,200699,197480],"requests":[12,12,12,12]},"video":{"bytes":[0,0,0,0],"requests":[0,0,0,0]},"other":{"bytes":[1259,1188,1192,1230],"requests":[6,5,5,6]}},"date":[1517563553,1517648692,1517735278,1517821390],"domElements":[1984,1983,1981,1981],"domInteractive":[3750,3565,3882,3168],"firstPaint":[3052,2759,3447,2171],"fullyLoaded":[11212,10797,11144,10752],"id":["180202_ZV_31b49e89cd5c5a6cb8ab1f4512b7b6c9","180203_JS_079888a78669b55b84c591548d56d48b","180204_88_e2e0ffe665a0a392849606f1906b060a","180205_Y5_b904d3463f6089512564a98f709f536c"],"loadTime":[3409,3384,3979,3190],"render":[2736,2608,3164,2048],"SpeedIndex":[4417,5104,5023,3879],"TTFB":[375,396,420,374],"videoFrames":[[{"_i":"frame_0000.jpg","_t":0,"_vc":0},{"_i":"frame_0027.jpg","_t":2700,"_vc":28},{"_i":"frame_0030.jpg","_t":3000,"_vc":80},{"_i":"frame_0042.jpg","_t":4200,"_vc":81},{"_i":"frame_0053.jpg","_t":5300,"_vc":81},{"_i":"frame_0078.jpg","_t":7800,"_vc":81},{"_i":"frame_0097.jpg","_t":9700,"_vc":81},{"_i":"frame_0104.jpg","_t":10400,"_vc":82},{"_i":"frame_0107.jpg","_t":10700,"_vc":96},{"_i":"frame_0111.jpg","_t":11100,"_vc":99},{"_i":"frame_0121.jpg","_t":12100,"_vc":99},{"_i":"frame_0122.jpg","_t":12200,"_vc":99},{"_i":"frame_0124.jpg","_t":12400,"_vc":100}],[{"_i":"frame_0000.jpg","_t":0,"_vc":0},{"_i":"frame_0026.jpg","_t":2600,"_vc":14},{"_i":"frame_0032.jpg","_t":3200,"_vc":67},{"_i":"frame_0036.jpg","_t":3600,"_vc":67},{"_i":"frame_0042.jpg","_t":4200,"_vc":67},{"_i":"frame_0049.jpg","_t":4900,"_vc":67},{"_i":"frame_0053.jpg","_t":5300,"_vc":68},{"_i":"frame_0074.jpg","_t":7400,"_vc":81},{"_i":"frame_0082.jpg","_t":8200,"_vc":81},{"_i":"frame_0084.jpg","_t":8400,"_vc":81},{"_i":"frame_0100.jpg","_t":10000,"_vc":82},{"_i":"frame_0102.jpg","_t":10200,"_vc":82},{"_i":"frame_0104.jpg","_t":10400,"_vc":82},{"_i":"frame_0107.jpg","_t":10700,"_vc":99},{"_i":"frame_0109.jpg","_t":10900,"_vc":99},{"_i":"frame_0110.jpg","_t":11000,"_vc":100},{"_i":"frame_0119.jpg","_t":11900,"_vc":100},{"_i":"frame_0121.jpg","_t":12100,"_vc":100},{"_i":"frame_0122.jpg","_t":12200,"_vc":100},{"_i":"frame_0124.jpg","_t":12400,"_vc":100},{"_i":"frame_0126.jpg","_t":12600,"_vc":100},{"_i":"frame_0127.jpg","_t":12700,"_vc":100}],[{"_i":"frame_0000.jpg","_t":0,"_vc":0},{"_i":"frame_0032.jpg","_t":3200,"_vc":28},{"_i":"frame_0038.jpg","_t":3800,"_vc":80},{"_i":"frame_0047.jpg","_t":4700,"_vc":81},{"_i":"frame_0050.jpg","_t":5000,"_vc":81},{"_i":"frame_0055.jpg","_t":5500,"_vc":81},{"_i":"frame_0076.jpg","_t":7600,"_vc":81},{"_i":"frame_0084.jpg","_t":8400,"_vc":81},{"_i":"frame_0098.jpg","_t":9800,"_vc":81},{"_i":"frame_0103.jpg","_t":10300,"_vc":81},{"_i":"frame_0104.jpg","_t":10400,"_vc":82},{"_i":"frame_0106.jpg","_t":10600,"_vc":82},{"_i":"frame_0108.jpg","_t":10800,"_vc":85},{"_i":"frame_0111.jpg","_t":11100,"_vc":99},{"_i":"frame_0112.jpg","_t":11200,"_vc":99},{"_i":"frame_0117.jpg","_t":11700,"_vc":99},{"_i":"frame_0119.jpg","_t":11900,"_vc":99},{"_i":"frame_0120.jpg","_t":12000,"_vc":99},{"_i":"frame_0122.jpg","_t":12200,"_vc":100},{"_i":"frame_0131.jpg","_t":13100,"_vc":100}],[{"_i":"frame_0000.jpg","_t":0,"_vc":0},{"_i":"frame_0020.jpg","_t":2000,"_vc":28},{"_i":"frame_0024.jpg","_t":2400,"_vc":80},{"_i":"frame_0026.jpg","_t":2600,"_vc":80},{"_i":"frame_0031.jpg","_t":3100,"_vc":80},{"_i":"frame_0039.jpg","_t":3900,"_vc":81},{"_i":"frame_0046.jpg","_t":4600,"_vc":81},{"_i":"frame_0048.jpg","_t":4800,"_vc":81},{"_i":"frame_0089.jpg","_t":8900,"_vc":81},{"_i":"frame_0091.jpg","_t":9100,"_vc":81},{"_i":"frame_0098.jpg","_t":9800,"_vc":82},{"_i":"frame_0101.jpg","_t":10100,"_vc":82},{"_i":"frame_0103.jpg","_t":10300,"_vc":85},{"_i":"frame_0104.jpg","_t":10400,"_vc":85},{"_i":"frame_0107.jpg","_t":10700,"_vc":99},{"_i":"frame_0112.jpg","_t":11200,"_vc":99},{"_i":"frame_0113.jpg","_t":11300,"_vc":99},{"_i":"frame_0115.jpg","_t":11500,"_vc":99},{"_i":"frame_0117.jpg","_t":11700,"_vc":99},{"_i":"frame_0118.jpg","_t":11800,"_vc":99},{"_i":"frame_0120.jpg","_t":12000,"_vc":99},{"_i":"frame_0121.jpg","_t":12100,"_vc":99},{"_i":"frame_0123.jpg","_t":12300,"_vc":99},{"_i":"frame_0124.jpg","_t":12400,"_vc":99},{"_i":"frame_0125.jpg","_t":12500,"_vc":99},{"_i":"frame_0127.jpg","_t":12700,"_vc":100}]],"visualComplete":[12400,11000,12200,12700],"lighthouse":[null,null,null,null],"pagespeed":[82,82,82,82]}}