{"_ts":[1523092625],"_r":{"breakdown":{"html":{"bytes":[48067],"requests":[18]},"js":{"bytes":[353927],"requests":[14]},"css":{"bytes":[79608],"requests":[3]},"image":{"bytes":[346643],"requests":[24]},"flash":{"bytes":[0],"requests":[0]},"font":{"bytes":[295634],"requests":[12]},"video":{"bytes":[0],"requests":[0]},"other":{"bytes":[4668],"requests":[6]}},"date":[1523092625],"domElements":[1940],"domInteractive":[2605],"firstPaint":[1803.4999999945],"fullyLoaded":[8494],"id":["180407_CG_c6e784f9c23fb546610287562ec4b3a3"],"loadTime":[2656],"render":[2300],"SpeedIndex":[2631],"TTFB":[505],"videoFrames":[[{"_i":"ms_000000.jpg","_t":0,"_vc":0},{"_i":"ms_002300.jpg","_t":2300,"_vc":94},{"_i":"ms_004100.jpg","_t":4100,"_vc":95},{"_i":"ms_008500.jpg","_t":8500,"_vc":100},{"_i":"ms_009200.jpg","_t":9200,"_vc":100},{"_i":"ms_010100.jpg","_t":10100,"_vc":99},{"_i":"ms_010200.jpg","_t":10200,"_vc":99},{"_i":"ms_010300.jpg","_t":10300,"_vc":99},{"_i":"ms_010400.jpg","_t":10400,"_vc":100},{"_i":"ms_010500.jpg","_t":10500,"_vc":100}]],"visualComplete":[8500],"lighthouse":[54],"pagespeed":[84]}}