{"_ts":[1543657924],"_r":{"breakdown":{"html":{"bytes":[47457],"requests":[27]},"js":{"bytes":[474882],"requests":[26]},"css":{"bytes":[79782],"requests":[3]},"image":{"bytes":[162800],"requests":[35]},"flash":{"bytes":[0],"requests":[0]},"font":{"bytes":[634592],"requests":[25]},"video":{"bytes":[0],"requests":[0]},"other":{"bytes":[6674],"requests":[11]}},"date":[1543657924],"domElements":[1960],"domInteractive":[3286],"firstPaint":[2288],"fullyLoaded":[11743],"id":["181201_F3_8eff07339cdce72be6a8dd99438c0ef1"],"loadTime":[5493],"render":[3000],"SpeedIndex":[4372],"TTFB":[727],"videoFrames":[[{"_i":"ms_000000.jpg","_t":0,"_vc":0},{"_i":"ms_003000.jpg","_t":3000,"_vc":84},{"_i":"ms_004500.jpg","_t":4500,"_vc":85},{"_i":"ms_007400.jpg","_t":7400,"_vc":83},{"_i":"ms_011500.jpg","_t":11500,"_vc":100},{"_i":"ms_012300.jpg","_t":12300,"_vc":100},{"_i":"ms_012400.jpg","_t":12400,"_vc":100},{"_i":"ms_012700.jpg","_t":12700,"_vc":100},{"_i":"ms_012900.jpg","_t":12900,"_vc":100},{"_i":"ms_013000.jpg","_t":13000,"_vc":100},{"_i":"ms_013100.jpg","_t":13100,"_vc":100},{"_i":"ms_013200.jpg","_t":13200,"_vc":100}]],"visualComplete":[11500],"lighthouse":[35],"pagespeed":[null]}}