{"_ts":[1507021525,1507114821,1507194398,1507291997,1507366996],"_r":{"breakdown":{"html":{"bytes":[0,89718,90303,91439,90493],"requests":[0,12,12,13,12]},"js":{"bytes":[0,379471,379453,377298,376779],"requests":[0,14,14,14,14]},"css":{"bytes":[0,72387,72387,72385,72384],"requests":[0,2,2,2,2]},"image":{"bytes":[0,848914,834253,833145,845705],"requests":[0,56,56,56,56]},"flash":{"bytes":[0,0,0,0,0],"requests":[0,0,0,0,0]},"font":{"bytes":[0,1017477,1017535,1017534,1017465],"requests":[0,45,45,45,45]},"other":{"bytes":[0,2376,2376,2376,2376],"requests":[0,3,3,3,3]}},"date":[1507021525,1507114821,1507194398,1507291997,1507366996],"domElements":[0,6910,6910,6911,6913],"domInteractive":[0,4737,4754,4501,4652],"firstPaint":[0,3250,3180,2947,3161],"fullyLoaded":[9459,11501,11338,11438,11104],"id":["171003_J7_e3dc1c7d5adbf1ad423da78326d35fb1","171004_XF_a7c1744bca9c44abeda8b522da3c7bb0","171005_S2_5ef129919e129cd0db4c6690ed7c8e3d","171006_NQ_50cfe2a59803587a7bdeb3d9d5c8f170","171007_TH_1a56883c699b71c6a7f4908e182c74af"],"loadTime":[3435,4958,5026,4870,4858],"render":[1587,3452,3245,3050,3443],"SpeedIndex":[4055,5510,5206,5476,5344],"TTFB":[0,891,1018,883,944],"videoFrames":[[{"_i":"frame_0000.jpg","_t":0,"_vc":0},{"_i":"frame_0016.jpg","_t":1600,"_vc":22},{"_i":"frame_0021.jpg","_t":2100,"_vc":65},{"_i":"frame_0048.jpg","_t":4800,"_vc":65},{"_i":"frame_0080.jpg","_t":8000,"_vc":100}],[{"_i":"frame_0000.jpg","_t":0,"_vc":0},{"_i":"frame_0035.jpg","_t":3500,"_vc":65},{"_i":"frame_0043.jpg","_t":4300,"_vc":65},{"_i":"frame_0065.jpg","_t":6500,"_vc":65},{"_i":"frame_0073.jpg","_t":7300,"_vc":66},{"_i":"frame_0093.jpg","_t":9300,"_vc":100}],[{"_i":"frame_0000.jpg","_t":0,"_vc":0},{"_i":"frame_0032.jpg","_t":3200,"_vc":66},{"_i":"frame_0041.jpg","_t":4100,"_vc":66},{"_i":"frame_0062.jpg","_t":6200,"_vc":66},{"_i":"frame_0077.jpg","_t":7700,"_vc":66},{"_i":"frame_0091.jpg","_t":9100,"_vc":100}],[{"_i":"frame_0000.jpg","_t":0,"_vc":0},{"_i":"frame_0031.jpg","_t":3100,"_vc":64},{"_i":"frame_0042.jpg","_t":4200,"_vc":64},{"_i":"frame_0057.jpg","_t":5700,"_vc":64},{"_i":"frame_0072.jpg","_t":7200,"_vc":64},{"_i":"frame_0097.jpg","_t":9700,"_vc":100}],[{"_i":"frame_0000.jpg","_t":0,"_vc":0},{"_i":"frame_0034.jpg","_t":3400,"_vc":64},{"_i":"frame_0043.jpg","_t":4300,"_vc":64},{"_i":"frame_0060.jpg","_t":6000,"_vc":64},{"_i":"frame_0072.jpg","_t":7200,"_vc":64},{"_i":"frame_0088.jpg","_t":8800,"_vc":100}]],"visualComplete":[8000,9300,9100,9700,8800],"lighthouse":[null,null,null,null,null],"pagespeed":[85,84,84,84,84]}}