{"_ts":[1512118990,1512205379],"_r":{"breakdown":{"html":{"bytes":[48126,46505],"requests":[18,17]},"js":{"bytes":[359794,358831],"requests":[13,12]},"css":{"bytes":[52378,52386],"requests":[2,2]},"image":{"bytes":[1465992,1466880],"requests":[49,51]},"flash":{"bytes":[0,0],"requests":[0,0]},"font":{"bytes":[347551,347529],"requests":[12,12]},"video":{"bytes":[0,0],"requests":[0,0]},"other":{"bytes":[2931,2911],"requests":[4,4]}},"date":[1512118990,1512205379],"domElements":[1644,1644],"domInteractive":[6360,4472],"firstPaint":[4046,4301],"fullyLoaded":[13305,11553],"id":["171201_41_47d0fbf0d6e89852414855443dc1b0fc","171202_SQ_d7613c3269b5a5023a240a82af04f070"],"loadTime":[12947,9485],"render":[4089,4389],"SpeedIndex":[5638,5351],"TTFB":[2709,2401],"videoFrames":[[{"_i":"frame_0000.jpg","_t":0,"_vc":0},{"_i":"frame_0041.jpg","_t":4100,"_vc":8},{"_i":"frame_0048.jpg","_t":4800,"_vc":8},{"_i":"frame_0050.jpg","_t":5000,"_vc":87},{"_i":"frame_0089.jpg","_t":8900,"_vc":87},{"_i":"frame_0102.jpg","_t":10200,"_vc":98},{"_i":"frame_0105.jpg","_t":10500,"_vc":99},{"_i":"frame_0133.jpg","_t":13300,"_vc":100}],[{"_i":"frame_0000.jpg","_t":0,"_vc":0},{"_i":"frame_0044.jpg","_t":4400,"_vc":8},{"_i":"frame_0049.jpg","_t":4900,"_vc":87},{"_i":"frame_0068.jpg","_t":6800,"_vc":87},{"_i":"frame_0086.jpg","_t":8600,"_vc":98},{"_i":"frame_0091.jpg","_t":9100,"_vc":100}]],"visualComplete":[13300,9100],"lighthouse":[null,null],"pagespeed":[66,66]}}