{"_ts":[1554109516,1554195937,1554282276,1554368793,1554455137],"_r":{"breakdown":{"html":{"bytes":[51787,52196,51762,51769,51774],"requests":[19,19,18,19,20]},"js":{"bytes":[531781,532222,532342,532456,529714],"requests":[26,26,26,26,26]},"css":{"bytes":[76533,76533,76533,76533,76533],"requests":[3,3,3,3,3]},"image":{"bytes":[187931,187931,187931,187931,187931],"requests":[28,28,28,28,28]},"flash":{"bytes":[0,0,0,0,0],"requests":[0,0,0,0,0]},"font":{"bytes":[634592,634592,634592,634592,634592],"requests":[25,25,25,25,25]},"video":{"bytes":[0,0,0,0,0],"requests":[0,0,0,0,0]},"other":{"bytes":[4049,3801,3795,4060,5198],"requests":[13,12,11,13,14]}},"date":[1554109516,1554195937,1554282276,1554368793,1554455137],"domElements":[2044,2044,2044,2041,2042],"domInteractive":[2441,2352,2330,2453,2286],"firstPaint":[1857.5899999996,1771.6549999968,1734.1300000044,1847.2099999999,1833.329999994],"fullyLoaded":[9295,8859,8414,9048,9109],"id":["190401_ZW_3d85f0fc655023683977b260cc42c2c9","190402_VZ_b092d2769580ae4e7df6e7bde84aa528","190403_FZ_bd99760741ee7a46b39722db8dcebc98","190404_GR_f895eeef9f8ffedc7bce0c0f15af2d36","190405_ZX_d78e5f555fd131cb54e3c480d0ae4669"],"loadTime":[7415,7093,6681,7024,7291],"render":[1900,1800,1700,1900,1800],"SpeedIndex":[2391,2276,2117,2388,2305],"TTFB":[665,722,769,703,161],"videoFrames":[[{"_i":"ms_000000.jpg","_t":0,"_vc":0},{"_i":"ms_001900.jpg","_t":1900,"_vc":53},{"_i":"ms_002000.jpg","_t":2000,"_vc":53},{"_i":"ms_002100.jpg","_t":2100,"_vc":88},{"_i":"ms_002200.jpg","_t":2200,"_vc":89},{"_i":"ms_002300.jpg","_t":2300,"_vc":89},{"_i":"ms_002400.jpg","_t":2400,"_vc":89},{"_i":"ms_002500.jpg","_t":2500,"_vc":89},{"_i":"ms_002600.jpg","_t":2600,"_vc":89},{"_i":"ms_002700.jpg","_t":2700,"_vc":89},{"_i":"ms_002800.jpg","_t":2800,"_vc":89},{"_i":"ms_002900.jpg","_t":2900,"_vc":89},{"_i":"ms_003000.jpg","_t":3000,"_vc":90},{"_i":"ms_003100.jpg","_t":3100,"_vc":90},{"_i":"ms_003200.jpg","_t":3200,"_vc":90},{"_i":"ms_003300.jpg","_t":3300,"_vc":90},{"_i":"ms_003400.jpg","_t":3400,"_vc":89},{"_i":"ms_003500.jpg","_t":3500,"_vc":89},{"_i":"ms_003600.jpg","_t":3600,"_vc":89},{"_i":"ms_003700.jpg","_t":3700,"_vc":89},{"_i":"ms_003800.jpg","_t":3800,"_vc":89},{"_i":"ms_003900.jpg","_t":3900,"_vc":89},{"_i":"ms_004000.jpg","_t":4000,"_vc":89},{"_i":"ms_004100.jpg","_t":4100,"_vc":90},{"_i":"ms_004200.jpg","_t":4200,"_vc":89},{"_i":"ms_004300.jpg","_t":4300,"_vc":89},{"_i":"ms_004400.jpg","_t":4400,"_vc":91},{"_i":"ms_004600.jpg","_t":4600,"_vc":91},{"_i":"ms_005200.jpg","_t":5200,"_vc":91},{"_i":"ms_005800.jpg","_t":5800,"_vc":99},{"_i":"ms_006100.jpg","_t":6100,"_vc":99},{"_i":"ms_007300.jpg","_t":7300,"_vc":99},{"_i":"ms_007500.jpg","_t":7500,"_vc":99},{"_i":"ms_007700.jpg","_t":7700,"_vc":99},{"_i":"ms_008000.jpg","_t":8000,"_vc":100},{"_i":"ms_008100.jpg","_t":8100,"_vc":100},{"_i":"ms_008200.jpg","_t":8200,"_vc":100},{"_i":"ms_008300.jpg","_t":8300,"_vc":100},{"_i":"ms_008400.jpg","_t":8400,"_vc":100},{"_i":"ms_008500.jpg","_t":8500,"_vc":100},{"_i":"ms_008600.jpg","_t":8600,"_vc":100},{"_i":"ms_008700.jpg","_t":8700,"_vc":100},{"_i":"ms_008800.jpg","_t":8800,"_vc":100},{"_i":"ms_009800.jpg","_t":9800,"_vc":100},{"_i":"ms_009900.jpg","_t":9900,"_vc":100},{"_i":"ms_010000.jpg","_t":10000,"_vc":100},{"_i":"ms_010100.jpg","_t":10100,"_vc":100},{"_i":"ms_010200.jpg","_t":10200,"_vc":100}],[{"_i":"ms_000000.jpg","_t":0,"_vc":0},{"_i":"ms_001800.jpg","_t":1800,"_vc":87},{"_i":"ms_001900.jpg","_t":1900,"_vc":87},{"_i":"ms_002000.jpg","_t":2000,"_vc":89},{"_i":"ms_002100.jpg","_t":2100,"_vc":89},{"_i":"ms_002200.jpg","_t":2200,"_vc":89},{"_i":"ms_002300.jpg","_t":2300,"_vc":89},{"_i":"ms_002500.jpg","_t":2500,"_vc":89},{"_i":"ms_002600.jpg","_t":2600,"_vc":89},{"_i":"ms_002700.jpg","_t":2700,"_vc":89},{"_i":"ms_002800.jpg","_t":2800,"_vc":90},{"_i":"ms_002900.jpg","_t":2900,"_vc":90},{"_i":"ms_003000.jpg","_t":3000,"_vc":90},{"_i":"ms_003100.jpg","_t":3100,"_vc":89},{"_i":"ms_003200.jpg","_t":3200,"_vc":89},{"_i":"ms_003300.jpg","_t":3300,"_vc":89},{"_i":"ms_003400.jpg","_t":3400,"_vc":89},{"_i":"ms_003500.jpg","_t":3500,"_vc":89},{"_i":"ms_003600.jpg","_t":3600,"_vc":90},{"_i":"ms_003700.jpg","_t":3700,"_vc":90},{"_i":"ms_003800.jpg","_t":3800,"_vc":90},{"_i":"ms_003900.jpg","_t":3900,"_vc":90},{"_i":"ms_004000.jpg","_t":4000,"_vc":89},{"_i":"ms_004100.jpg","_t":4100,"_vc":89},{"_i":"ms_004300.jpg","_t":4300,"_vc":89},{"_i":"ms_005300.jpg","_t":5300,"_vc":89},{"_i":"ms_005500.jpg","_t":5500,"_vc":89},{"_i":"ms_006000.jpg","_t":6000,"_vc":99},{"_i":"ms_006500.jpg","_t":6500,"_vc":100},{"_i":"ms_006700.jpg","_t":6700,"_vc":100},{"_i":"ms_006800.jpg","_t":6800,"_vc":99},{"_i":"ms_007000.jpg","_t":7000,"_vc":99},{"_i":"ms_007500.jpg","_t":7500,"_vc":99},{"_i":"ms_008000.jpg","_t":8000,"_vc":100},{"_i":"ms_008500.jpg","_t":8500,"_vc":100},{"_i":"ms_009700.jpg","_t":9700,"_vc":100},{"_i":"ms_010000.jpg","_t":10000,"_vc":100},{"_i":"ms_010100.jpg","_t":10100,"_vc":100}],[{"_i":"ms_000000.jpg","_t":0,"_vc":0},{"_i":"ms_001700.jpg","_t":1700,"_vc":86},{"_i":"ms_001800.jpg","_t":1800,"_vc":86},{"_i":"ms_002000.jpg","_t":2000,"_vc":89},{"_i":"ms_002100.jpg","_t":2100,"_vc":89},{"_i":"ms_002200.jpg","_t":2200,"_vc":89},{"_i":"ms_002300.jpg","_t":2300,"_vc":89},{"_i":"ms_002400.jpg","_t":2400,"_vc":89},{"_i":"ms_002500.jpg","_t":2500,"_vc":89},{"_i":"ms_002700.jpg","_t":2700,"_vc":89},{"_i":"ms_002800.jpg","_t":2800,"_vc":90},{"_i":"ms_002900.jpg","_t":2900,"_vc":91},{"_i":"ms_003000.jpg","_t":3000,"_vc":90},{"_i":"ms_003100.jpg","_t":3100,"_vc":89},{"_i":"ms_003200.jpg","_t":3200,"_vc":89},{"_i":"ms_003300.jpg","_t":3300,"_vc":89},{"_i":"ms_003400.jpg","_t":3400,"_vc":89},{"_i":"ms_003500.jpg","_t":3500,"_vc":89},{"_i":"ms_003600.jpg","_t":3600,"_vc":90},{"_i":"ms_003700.jpg","_t":3700,"_vc":90},{"_i":"ms_003800.jpg","_t":3800,"_vc":90},{"_i":"ms_003900.jpg","_t":3900,"_vc":90},{"_i":"ms_004000.jpg","_t":4000,"_vc":89},{"_i":"ms_004100.jpg","_t":4100,"_vc":89},{"_i":"ms_004500.jpg","_t":4500,"_vc":89},{"_i":"ms_004700.jpg","_t":4700,"_vc":89},{"_i":"ms_004900.jpg","_t":4900,"_vc":89},{"_i":"ms_005100.jpg","_t":5100,"_vc":89},{"_i":"ms_005300.jpg","_t":5300,"_vc":99},{"_i":"ms_006300.jpg","_t":6300,"_vc":99},{"_i":"ms_006800.jpg","_t":6800,"_vc":99},{"_i":"ms_007200.jpg","_t":7200,"_vc":99},{"_i":"ms_007300.jpg","_t":7300,"_vc":100},{"_i":"ms_007400.jpg","_t":7400,"_vc":100},{"_i":"ms_007500.jpg","_t":7500,"_vc":100},{"_i":"ms_007600.jpg","_t":7600,"_vc":100},{"_i":"ms_007700.jpg","_t":7700,"_vc":100},{"_i":"ms_007800.jpg","_t":7800,"_vc":100},{"_i":"ms_007900.jpg","_t":7900,"_vc":100},{"_i":"ms_008000.jpg","_t":8000,"_vc":100},{"_i":"ms_008100.jpg","_t":8100,"_vc":100},{"_i":"ms_008200.jpg","_t":8200,"_vc":100},{"_i":"ms_008300.jpg","_t":8300,"_vc":100},{"_i":"ms_008400.jpg","_t":8400,"_vc":100},{"_i":"ms_008500.jpg","_t":8500,"_vc":100},{"_i":"ms_008600.jpg","_t":8600,"_vc":100},{"_i":"ms_008700.jpg","_t":8700,"_vc":100}],[{"_i":"ms_000000.jpg","_t":0,"_vc":0},{"_i":"ms_001900.jpg","_t":1900,"_vc":71},{"_i":"ms_002000.jpg","_t":2000,"_vc":71},{"_i":"ms_002100.jpg","_t":2100,"_vc":88},{"_i":"ms_002200.jpg","_t":2200,"_vc":89},{"_i":"ms_002300.jpg","_t":2300,"_vc":89},{"_i":"ms_002400.jpg","_t":2400,"_vc":89},{"_i":"ms_002500.jpg","_t":2500,"_vc":89},{"_i":"ms_002600.jpg","_t":2600,"_vc":89},{"_i":"ms_002700.jpg","_t":2700,"_vc":89},{"_i":"ms_002800.jpg","_t":2800,"_vc":89},{"_i":"ms_002900.jpg","_t":2900,"_vc":90},{"_i":"ms_003000.jpg","_t":3000,"_vc":89},{"_i":"ms_003100.jpg","_t":3100,"_vc":89},{"_i":"ms_003200.jpg","_t":3200,"_vc":89},{"_i":"ms_003300.jpg","_t":3300,"_vc":89},{"_i":"ms_003400.jpg","_t":3400,"_vc":89},{"_i":"ms_003500.jpg","_t":3500,"_vc":89},{"_i":"ms_003600.jpg","_t":3600,"_vc":90},{"_i":"ms_003700.jpg","_t":3700,"_vc":90},{"_i":"ms_003800.jpg","_t":3800,"_vc":90},{"_i":"ms_003900.jpg","_t":3900,"_vc":90},{"_i":"ms_004100.jpg","_t":4100,"_vc":89},{"_i":"ms_004300.jpg","_t":4300,"_vc":89},{"_i":"ms_005100.jpg","_t":5100,"_vc":89},{"_i":"ms_005200.jpg","_t":5200,"_vc":89},{"_i":"ms_005300.jpg","_t":5300,"_vc":89},{"_i":"ms_005400.jpg","_t":5400,"_vc":89},{"_i":"ms_005700.jpg","_t":5700,"_vc":89},{"_i":"ms_005800.jpg","_t":5800,"_vc":96},{"_i":"ms_006000.jpg","_t":6000,"_vc":99},{"_i":"ms_006500.jpg","_t":6500,"_vc":99},{"_i":"ms_006600.jpg","_t":6600,"_vc":99},{"_i":"ms_006700.jpg","_t":6700,"_vc":99},{"_i":"ms_006800.jpg","_t":6800,"_vc":99},{"_i":"ms_006900.jpg","_t":6900,"_vc":99},{"_i":"ms_007000.jpg","_t":7000,"_vc":99},{"_i":"ms_007500.jpg","_t":7500,"_vc":99},{"_i":"ms_008000.jpg","_t":8000,"_vc":100},{"_i":"ms_008500.jpg","_t":8500,"_vc":100},{"_i":"ms_009700.jpg","_t":9700,"_vc":100},{"_i":"ms_009900.jpg","_t":9900,"_vc":100}],[{"_i":"ms_000000.jpg","_t":0,"_vc":0},{"_i":"ms_001800.jpg","_t":1800,"_vc":71},{"_i":"ms_001900.jpg","_t":1900,"_vc":71},{"_i":"ms_002000.jpg","_t":2000,"_vc":72},{"_i":"ms_002100.jpg","_t":2100,"_vc":89},{"_i":"ms_002200.jpg","_t":2200,"_vc":89},{"_i":"ms_002300.jpg","_t":2300,"_vc":89},{"_i":"ms_002400.jpg","_t":2400,"_vc":89},{"_i":"ms_002500.jpg","_t":2500,"_vc":89},{"_i":"ms_002600.jpg","_t":2600,"_vc":89},{"_i":"ms_002700.jpg","_t":2700,"_vc":90},{"_i":"ms_002800.jpg","_t":2800,"_vc":90},{"_i":"ms_002900.jpg","_t":2900,"_vc":90},{"_i":"ms_003000.jpg","_t":3000,"_vc":90},{"_i":"ms_003100.jpg","_t":3100,"_vc":90},{"_i":"ms_003200.jpg","_t":3200,"_vc":90},{"_i":"ms_003300.jpg","_t":3300,"_vc":90},{"_i":"ms_003400.jpg","_t":3400,"_vc":90},{"_i":"ms_003600.jpg","_t":3600,"_vc":91},{"_i":"ms_003700.jpg","_t":3700,"_vc":90},{"_i":"ms_003800.jpg","_t":3800,"_vc":90},{"_i":"ms_003900.jpg","_t":3900,"_vc":90},{"_i":"ms_004000.jpg","_t":4000,"_vc":89},{"_i":"ms_004700.jpg","_t":4700,"_vc":89},{"_i":"ms_005300.jpg","_t":5300,"_vc":89},{"_i":"ms_005800.jpg","_t":5800,"_vc":99},{"_i":"ms_006500.jpg","_t":6500,"_vc":99},{"_i":"ms_006600.jpg","_t":6600,"_vc":99},{"_i":"ms_006700.jpg","_t":6700,"_vc":100},{"_i":"ms_006800.jpg","_t":6800,"_vc":99},{"_i":"ms_007000.jpg","_t":7000,"_vc":99},{"_i":"ms_007500.jpg","_t":7500,"_vc":99},{"_i":"ms_008000.jpg","_t":8000,"_vc":99},{"_i":"ms_008500.jpg","_t":8500,"_vc":100},{"_i":"ms_009700.jpg","_t":9700,"_vc":100},{"_i":"ms_010000.jpg","_t":10000,"_vc":100},{"_i":"ms_010100.jpg","_t":10100,"_vc":100}]],"visualComplete":[8000,6500,7300,8000,6700],"lighthouse":[35,35,35,35,35],"pagespeed":[84,84,84,84,84]}}