{"_ts":[1538384541],"_r":{"breakdown":{"html":{"bytes":[95480],"requests":[26]},"js":{"bytes":[485744],"requests":[14]},"css":{"bytes":[77521],"requests":[2]},"image":{"bytes":[812967],"requests":[35]},"flash":{"bytes":[0],"requests":[0]},"font":{"bytes":[467839],"requests":[14]},"video":{"bytes":[0],"requests":[0]},"other":{"bytes":[7710],"requests":[8]}},"date":[1538384541],"domElements":[4836],"domInteractive":[4946],"firstPaint":[6385],"fullyLoaded":[27309],"id":["181001_41_3331d747d8742b0e8541202e6b5331ff"],"loadTime":[22706],"render":[6590],"SpeedIndex":[17241],"TTFB":[3359],"videoFrames":[[{"_i":"frame_0000.jpg","_t":0,"_vc":0},{"_i":"frame_0066.jpg","_t":6600,"_vc":23},{"_i":"frame_0204.jpg","_t":20400,"_vc":99},{"_i":"frame_0219.jpg","_t":21900,"_vc":100}]],"visualComplete":[21900],"lighthouse":[null],"pagespeed":[57]}}