{"_ts":[1533085536],"_r":{"breakdown":{"html":{"bytes":[42983],"requests":[17]},"js":{"bytes":[403256],"requests":[13]},"css":{"bytes":[54095],"requests":[2]},"image":{"bytes":[883993],"requests":[47]},"flash":{"bytes":[0],"requests":[0]},"font":{"bytes":[464532],"requests":[13]},"video":{"bytes":[0],"requests":[0]},"other":{"bytes":[5671],"requests":[6]}},"date":[1533085536],"domElements":[1978],"domInteractive":[4626],"firstPaint":[5156],"fullyLoaded":[18099],"id":["180801_26_6a8c3b8d5f2b7a23ac1e20cc6f5665bb"],"loadTime":[6272],"render":[5684],"SpeedIndex":[6022],"TTFB":[3351],"videoFrames":[[{"_i":"frame_0000.jpg","_t":0,"_vc":0},{"_i":"frame_0057.jpg","_t":5700,"_vc":95},{"_i":"frame_0063.jpg","_t":6300,"_vc":95},{"_i":"frame_0068.jpg","_t":6800,"_vc":95},{"_i":"frame_0101.jpg","_t":10100,"_vc":95},{"_i":"frame_0120.jpg","_t":12000,"_vc":99},{"_i":"frame_0127.jpg","_t":12700,"_vc":100}]],"visualComplete":[12700],"lighthouse":[null],"pagespeed":[78]}}