{"_ts":[1543628203,1543714605,1543800809],"_r":{"breakdown":{"html":{"bytes":[53430,53413,53424],"requests":[30,30,27]},"js":{"bytes":[442938,442938,443098],"requests":[15,15,15]},"css":{"bytes":[79782,79782,79782],"requests":[3,3,3]},"image":{"bytes":[182098,181853,181900],"requests":[41,34,35]},"flash":{"bytes":[0,0,0],"requests":[0,0,0]},"font":{"bytes":[348532,348532,348532],"requests":[13,13,13]},"video":{"bytes":[0,0,0],"requests":[0,0,0]},"other":{"bytes":[6859,6871,6841],"requests":[11,11,12]}},"date":[1543628203,1543714605,1543800809],"domElements":[2066,2067,2066],"domInteractive":[3143,3443,3211],"firstPaint":[2283.500000005,2680.8999999994,2454.4000000024],"fullyLoaded":[11066,11117,10560],"id":["181201_5H_59de0e6673aa4733104dc89385e74345","181202_JV_fdb3f8a715cbb57a83866b101132cf3a","181203_3H_47fbdc3ad319a70b2b26fda60932f02c"],"loadTime":[3299,3556,3371],"render":[3300,2600,2900],"SpeedIndex":[4487,4204,4049],"TTFB":[530,663,937],"videoFrames":[[{"_i":"ms_000000.jpg","_t":0,"_vc":0},{"_i":"ms_003300.jpg","_t":3300,"_vc":85},{"_i":"ms_006700.jpg","_t":6700,"_vc":85},{"_i":"ms_011200.jpg","_t":11200,"_vc":100},{"_i":"ms_011900.jpg","_t":11900,"_vc":100},{"_i":"ms_012000.jpg","_t":12000,"_vc":100},{"_i":"ms_012400.jpg","_t":12400,"_vc":100},{"_i":"ms_012500.jpg","_t":12500,"_vc":100},{"_i":"ms_012600.jpg","_t":12600,"_vc":100},{"_i":"ms_012700.jpg","_t":12700,"_vc":100},{"_i":"ms_012800.jpg","_t":12800,"_vc":100},{"_i":"ms_012900.jpg","_t":12900,"_vc":100},{"_i":"ms_013000.jpg","_t":13000,"_vc":99},{"_i":"ms_013100.jpg","_t":13100,"_vc":100},{"_i":"ms_013200.jpg","_t":13200,"_vc":99},{"_i":"ms_013300.jpg","_t":13300,"_vc":100}],[{"_i":"ms_000000.jpg","_t":0,"_vc":0},{"_i":"ms_002600.jpg","_t":2600,"_vc":39},{"_i":"ms_003500.jpg","_t":3500,"_vc":85},{"_i":"ms_005500.jpg","_t":5500,"_vc":85},{"_i":"ms_009600.jpg","_t":9600,"_vc":93},{"_i":"ms_011600.jpg","_t":11600,"_vc":100},{"_i":"ms_011900.jpg","_t":11900,"_vc":100},{"_i":"ms_012300.jpg","_t":12300,"_vc":100},{"_i":"ms_012400.jpg","_t":12400,"_vc":100},{"_i":"ms_012500.jpg","_t":12500,"_vc":100},{"_i":"ms_012600.jpg","_t":12600,"_vc":100},{"_i":"ms_012700.jpg","_t":12700,"_vc":100},{"_i":"ms_012800.jpg","_t":12800,"_vc":100},{"_i":"ms_012900.jpg","_t":12900,"_vc":100},{"_i":"ms_013000.jpg","_t":13000,"_vc":100},{"_i":"ms_013100.jpg","_t":13100,"_vc":100},{"_i":"ms_013200.jpg","_t":13200,"_vc":100},{"_i":"ms_013300.jpg","_t":13300,"_vc":100},{"_i":"ms_013400.jpg","_t":13400,"_vc":100},{"_i":"ms_013500.jpg","_t":13500,"_vc":100}],[{"_i":"ms_000000.jpg","_t":0,"_vc":0},{"_i":"ms_002900.jpg","_t":2900,"_vc":85},{"_i":"ms_005400.jpg","_t":5400,"_vc":85},{"_i":"ms_010000.jpg","_t":10000,"_vc":93},{"_i":"ms_011200.jpg","_t":11200,"_vc":100},{"_i":"ms_011700.jpg","_t":11700,"_vc":100},{"_i":"ms_011800.jpg","_t":11800,"_vc":100},{"_i":"ms_011900.jpg","_t":11900,"_vc":100},{"_i":"ms_012000.jpg","_t":12000,"_vc":100},{"_i":"ms_012100.jpg","_t":12100,"_vc":100},{"_i":"ms_012200.jpg","_t":12200,"_vc":100},{"_i":"ms_012300.jpg","_t":12300,"_vc":100},{"_i":"ms_012400.jpg","_t":12400,"_vc":100},{"_i":"ms_012500.jpg","_t":12500,"_vc":100},{"_i":"ms_012600.jpg","_t":12600,"_vc":100},{"_i":"ms_012700.jpg","_t":12700,"_vc":100},{"_i":"ms_012800.jpg","_t":12800,"_vc":100},{"_i":"ms_012900.jpg","_t":12900,"_vc":100}]],"visualComplete":[11200,11600,11200],"lighthouse":[31,31,31],"pagespeed":[null,82,null]}}