{"_ts":[1530407078,1530493476,1530580013,1530666508],"_r":{"breakdown":{"html":{"bytes":[64502,64469,64490,64435],"requests":[24,24,24,24]},"js":{"bytes":[414374,414288,415062,414877],"requests":[15,15,15,15]},"css":{"bytes":[88565,88565,88565,88565],"requests":[3,3,3,3]},"image":{"bytes":[198461,198470,198463,198446],"requests":[29,29,29,29]},"flash":{"bytes":[0,0,0,0],"requests":[0,0,0,0]},"font":{"bytes":[464524,464532,464524,464532],"requests":[13,13,13,13]},"video":{"bytes":[0,0,0,0],"requests":[0,0,0,0]},"other":{"bytes":[7199,7218,7218,7199],"requests":[8,8,8,8]}},"date":[1530407078,1530493476,1530580013,1530666508],"domElements":[1973,1972,1972,1972],"domInteractive":[4375,4942,4142,5153],"firstPaint":[4000,4590,3784,4787],"fullyLoaded":[15814,14737,15539,15948],"id":["180701_JW_904a295c7d3bbcfeb7e6d6afd7a0bb60","180702_SX_f4ed696d3b6c7d13aac04029ca8cf5ba","180703_9N_331148d09679eb9206e22079b5ae094b","180704_8R_baf48e2f122db115b19f51de1f391e3c"],"loadTime":[4579,4952,4152,5159],"render":[4189,4684,3888,4901],"SpeedIndex":[6260,6547,5772,6755],"TTFB":[2441,2678,2164,3183],"videoFrames":[[{"_i":"frame_0000.jpg","_t":0,"_vc":0},{"_i":"frame_0042.jpg","_t":4200,"_vc":15},{"_i":"frame_0056.jpg","_t":5600,"_vc":87},{"_i":"frame_0086.jpg","_t":8600,"_vc":88},{"_i":"frame_0106.jpg","_t":10600,"_vc":95},{"_i":"frame_0114.jpg","_t":11400,"_vc":96},{"_i":"frame_0133.jpg","_t":13300,"_vc":96},{"_i":"frame_0135.jpg","_t":13500,"_vc":96},{"_i":"frame_0141.jpg","_t":14100,"_vc":96},{"_i":"frame_0147.jpg","_t":14700,"_vc":96},{"_i":"frame_0148.jpg","_t":14800,"_vc":96},{"_i":"frame_0150.jpg","_t":15000,"_vc":96},{"_i":"frame_0152.jpg","_t":15200,"_vc":96},{"_i":"frame_0153.jpg","_t":15300,"_vc":96},{"_i":"frame_0154.jpg","_t":15400,"_vc":96},{"_i":"frame_0155.jpg","_t":15500,"_vc":96},{"_i":"frame_0156.jpg","_t":15600,"_vc":96},{"_i":"frame_0158.jpg","_t":15800,"_vc":96},{"_i":"frame_0159.jpg","_t":15900,"_vc":96},{"_i":"frame_0161.jpg","_t":16100,"_vc":99},{"_i":"frame_0163.jpg","_t":16300,"_vc":99},{"_i":"frame_0173.jpg","_t":17300,"_vc":100},{"_i":"frame_0174.jpg","_t":17400,"_vc":100},{"_i":"frame_0176.jpg","_t":17600,"_vc":100},{"_i":"frame_0177.jpg","_t":17700,"_vc":100}],[{"_i":"frame_0000.jpg","_t":0,"_vc":0},{"_i":"frame_0047.jpg","_t":4700,"_vc":15},{"_i":"frame_0060.jpg","_t":6000,"_vc":88},{"_i":"frame_0088.jpg","_t":8800,"_vc":88},{"_i":"frame_0106.jpg","_t":10600,"_vc":95},{"_i":"frame_0112.jpg","_t":11200,"_vc":96},{"_i":"frame_0119.jpg","_t":11900,"_vc":96},{"_i":"frame_0127.jpg","_t":12700,"_vc":96},{"_i":"frame_0129.jpg","_t":12900,"_vc":96},{"_i":"frame_0132.jpg","_t":13200,"_vc":96},{"_i":"frame_0136.jpg","_t":13600,"_vc":96},{"_i":"frame_0138.jpg","_t":13800,"_vc":96},{"_i":"frame_0139.jpg","_t":13900,"_vc":96},{"_i":"frame_0140.jpg","_t":14000,"_vc":96},{"_i":"frame_0142.jpg","_t":14200,"_vc":96},{"_i":"frame_0143.jpg","_t":14300,"_vc":96},{"_i":"frame_0145.jpg","_t":14500,"_vc":96},{"_i":"frame_0146.jpg","_t":14600,"_vc":96},{"_i":"frame_0148.jpg","_t":14800,"_vc":96},{"_i":"frame_0149.jpg","_t":14900,"_vc":99},{"_i":"frame_0151.jpg","_t":15100,"_vc":99},{"_i":"frame_0161.jpg","_t":16100,"_vc":100},{"_i":"frame_0162.jpg","_t":16200,"_vc":100},{"_i":"frame_0163.jpg","_t":16300,"_vc":100},{"_i":"frame_0165.jpg","_t":16500,"_vc":100}],[{"_i":"frame_0000.jpg","_t":0,"_vc":0},{"_i":"frame_0039.jpg","_t":3900,"_vc":15},{"_i":"frame_0051.jpg","_t":5100,"_vc":88},{"_i":"frame_0082.jpg","_t":8200,"_vc":88},{"_i":"frame_0102.jpg","_t":10200,"_vc":95},{"_i":"frame_0114.jpg","_t":11400,"_vc":96},{"_i":"frame_0130.jpg","_t":13000,"_vc":96},{"_i":"frame_0131.jpg","_t":13100,"_vc":96},{"_i":"frame_0135.jpg","_t":13500,"_vc":96},{"_i":"frame_0138.jpg","_t":13800,"_vc":96},{"_i":"frame_0139.jpg","_t":13900,"_vc":96},{"_i":"frame_0140.jpg","_t":14000,"_vc":96},{"_i":"frame_0141.jpg","_t":14100,"_vc":96},{"_i":"frame_0142.jpg","_t":14200,"_vc":96},{"_i":"frame_0143.jpg","_t":14300,"_vc":96},{"_i":"frame_0145.jpg","_t":14500,"_vc":96},{"_i":"frame_0147.jpg","_t":14700,"_vc":96},{"_i":"frame_0149.jpg","_t":14900,"_vc":96},{"_i":"frame_0150.jpg","_t":15000,"_vc":96},{"_i":"frame_0152.jpg","_t":15200,"_vc":96},{"_i":"frame_0154.jpg","_t":15400,"_vc":96},{"_i":"frame_0155.jpg","_t":15500,"_vc":96},{"_i":"frame_0156.jpg","_t":15600,"_vc":96},{"_i":"frame_0157.jpg","_t":15700,"_vc":99},{"_i":"frame_0165.jpg","_t":16500,"_vc":100},{"_i":"frame_0166.jpg","_t":16600,"_vc":100},{"_i":"frame_0168.jpg","_t":16800,"_vc":100},{"_i":"frame_0169.jpg","_t":16900,"_vc":100}],[{"_i":"frame_0000.jpg","_t":0,"_vc":0},{"_i":"frame_0049.jpg","_t":4900,"_vc":15},{"_i":"frame_0061.jpg","_t":6100,"_vc":88},{"_i":"frame_0094.jpg","_t":9400,"_vc":88},{"_i":"frame_0113.jpg","_t":11300,"_vc":95},{"_i":"frame_0119.jpg","_t":11900,"_vc":96},{"_i":"frame_0130.jpg","_t":13000,"_vc":96},{"_i":"frame_0132.jpg","_t":13200,"_vc":96},{"_i":"frame_0133.jpg","_t":13300,"_vc":96},{"_i":"frame_0135.jpg","_t":13500,"_vc":96},{"_i":"frame_0153.jpg","_t":15300,"_vc":96},{"_i":"frame_0155.jpg","_t":15500,"_vc":96},{"_i":"frame_0157.jpg","_t":15700,"_vc":96},{"_i":"frame_0159.jpg","_t":15900,"_vc":96},{"_i":"frame_0160.jpg","_t":16000,"_vc":96},{"_i":"frame_0161.jpg","_t":16100,"_vc":100},{"_i":"frame_0162.jpg","_t":16200,"_vc":100},{"_i":"frame_0163.jpg","_t":16300,"_vc":100},{"_i":"frame_0165.jpg","_t":16500,"_vc":99},{"_i":"frame_0167.jpg","_t":16700,"_vc":99},{"_i":"frame_0178.jpg","_t":17800,"_vc":100},{"_i":"frame_0179.jpg","_t":17900,"_vc":100},{"_i":"frame_0180.jpg","_t":18000,"_vc":100}]],"visualComplete":[17300,16100,16500,16100],"lighthouse":[null,null,null,null],"pagespeed":[84,84,84,84]}}