{"_ts":[1504551763,1504638147],"_r":{"breakdown":{"html":{"bytes":[72604,73016],"requests":[13,13]},"js":{"bytes":[328924,328890],"requests":[10,10]},"css":{"bytes":[71465,71472],"requests":[2,2]},"image":{"bytes":[989504,990446],"requests":[57,59]},"flash":{"bytes":[0,0],"requests":[0,0]},"font":{"bytes":[320249,320152],"requests":[12,12]},"other":{"bytes":[1696,2109],"requests":[2,3]}},"date":[1504551763,1504638147],"domElements":[2580,2580],"domInteractive":[8019,7128],"firstPaint":[5153,5699],"fullyLoaded":[18566,15536],"id":["170904_J7_b9518aa61fbcd0fff6a622e5dc3e78d5","170905_61_922ebace8f6cb8c2cdc1e821bcdd00ca"],"loadTime":[8072,7135],"render":[6885,10374],"SpeedIndex":[10674,11060],"TTFB":[2653,2468],"videoFrames":[[{"_i":"frame_0000.jpg","_t":0,"_vc":0},{"_i":"frame_0069.jpg","_t":6900,"_vc":52},{"_i":"frame_0132.jpg","_t":13200,"_vc":70},{"_i":"frame_0157.jpg","_t":15700,"_vc":100}],[{"_i":"frame_0000.jpg","_t":0,"_vc":0},{"_i":"frame_0104.jpg","_t":10400,"_vc":70},{"_i":"frame_0126.jpg","_t":12600,"_vc":100}]],"visualComplete":[15700,12600],"lighthouse":[null,null],"pagespeed":[87,87]}}