{"_ts":[1523070461,1523117460],"_r":{"breakdown":{"html":{"bytes":[35514,48048],"requests":[16,18]},"js":{"bytes":[354558,354387],"requests":[14,14]},"css":{"bytes":[79608,79608],"requests":[3,3]},"image":{"bytes":[307060,346635],"requests":[22,24]},"flash":{"bytes":[0,0],"requests":[0,0]},"font":{"bytes":[295634,295636],"requests":[12,12]},"video":{"bytes":[0,0],"requests":[0,0]},"other":{"bytes":[5324,4621],"requests":[7,6]}},"date":[1523070461,1523117460],"domElements":[1867,1940],"domInteractive":[2765,2403],"firstPaint":[1794.9000000008,1615.3000000013],"fullyLoaded":[11525,7694],"id":["180406_53_370a9d94642910f750cf069001a56e06","180407_CJ_569ed491baff3c7630c83c8d595ad5c6"],"loadTime":[2818,2510],"render":[1900,1700],"SpeedIndex":[2429,2029],"TTFB":[480,451],"videoFrames":[[{"_i":"ms_000000.jpg","_t":0,"_vc":0},{"_i":"ms_001900.jpg","_t":1900,"_vc":40},{"_i":"ms_002700.jpg","_t":2700,"_vc":98},{"_i":"ms_003900.jpg","_t":3900,"_vc":99},{"_i":"ms_006100.jpg","_t":6100,"_vc":100},{"_i":"ms_008200.jpg","_t":8200,"_vc":100},{"_i":"ms_008500.jpg","_t":8500,"_vc":100},{"_i":"ms_009800.jpg","_t":9800,"_vc":99},{"_i":"ms_009900.jpg","_t":9900,"_vc":99},{"_i":"ms_010000.jpg","_t":10000,"_vc":99},{"_i":"ms_010100.jpg","_t":10100,"_vc":100},{"_i":"ms_010200.jpg","_t":10200,"_vc":100}],[{"_i":"ms_000000.jpg","_t":0,"_vc":0},{"_i":"ms_001700.jpg","_t":1700,"_vc":93},{"_i":"ms_002600.jpg","_t":2600,"_vc":94},{"_i":"ms_004900.jpg","_t":4900,"_vc":96},{"_i":"ms_007900.jpg","_t":7900,"_vc":99},{"_i":"ms_008400.jpg","_t":8400,"_vc":100},{"_i":"ms_009600.jpg","_t":9600,"_vc":99},{"_i":"ms_009700.jpg","_t":9700,"_vc":99},{"_i":"ms_009800.jpg","_t":9800,"_vc":99},{"_i":"ms_009900.jpg","_t":9900,"_vc":100},{"_i":"ms_010000.jpg","_t":10000,"_vc":100}]],"visualComplete":[6100,8400],"lighthouse":[54,54],"pagespeed":[84,84]}}