{"_ts":[1505497827,1505585065,1505667371,1505845745,1505929040,1506014703,1506101683],"_r":{"breakdown":{"html":{"bytes":[67056,75451,65701,75993,76409,66326,67269],"requests":[17,15,15,15,16,15,16]},"js":{"bytes":[325141,334352,325559,336598,336991,348804,349785],"requests":[10,10,10,10,10,10,10]},"css":{"bytes":[81896,73441,81901,73441,73441,83067,83068],"requests":[3,2,3,2,2,3,3]},"image":{"bytes":[691291,664134,691193,663863,663986,681392,681536],"requests":[28,28,28,28,28,27,27]},"flash":{"bytes":[0,0,0,0,0,0,0],"requests":[0,0,0,0,0,0,0]},"font":{"bytes":[143963,221346,143965,221329,221332,273787,273787],"requests":[6,7,6,7,7,12,12]},"other":{"bytes":[6979,6959,6981,6692,6384,6554,6552],"requests":[4,4,4,4,4,4,4]}},"date":[1505497827,1505585065,1505667371,1505845745,1505929040,1506014703,1506101683],"domElements":[1710,1989,1709,1989,1990,1715,1716],"domInteractive":[3227,2933,3000,3346,3109,2794,2894],"firstPaint":[1997,2067,2134,2081,1841,1806,2581],"fullyLoaded":[8568,9614,10196,8879,8860,9316,9473],"id":["170915_DS_35f6721f36b03507cf666e1472dc9723","170916_0Q_f14c77b3f1d4301855e91b6fc3272bfb","170917_MS_e9b89bff4a971c7d56f833a47e8e0acb","170919_Y4_3f82420372144d96ab22ba1da990e2d8","170920_0C_0ae5fcaf36f9c790a2b6dfb1b7368fa9","170921_S0_24c8b49a537847d8efa92331162763ea","170922_YT_0bb1a606afeb60f0e194337c04e81450"],"loadTime":[3361,3790,3401,4344,3645,3125,3537],"render":[2156,2660,2748,2256,1957,1959,2761],"SpeedIndex":[3773,6823,4982,6521,6560,3563,3928],"TTFB":[646,663,566,685,574,585,550],"videoFrames":[[{"_i":"frame_0000.jpg","_t":0,"_vc":0},{"_i":"frame_0022.jpg","_t":2200,"_vc":8},{"_i":"frame_0028.jpg","_t":2800,"_vc":76},{"_i":"frame_0037.jpg","_t":3700,"_vc":76},{"_i":"frame_0042.jpg","_t":4200,"_vc":76},{"_i":"frame_0044.jpg","_t":4400,"_vc":76},{"_i":"frame_0069.jpg","_t":6900,"_vc":99},{"_i":"frame_0073.jpg","_t":7300,"_vc":99},{"_i":"frame_0078.jpg","_t":7800,"_vc":99},{"_i":"frame_0087.jpg","_t":8700,"_vc":99},{"_i":"frame_0089.jpg","_t":8900,"_vc":99},{"_i":"frame_0091.jpg","_t":9100,"_vc":99},{"_i":"frame_0093.jpg","_t":9300,"_vc":99},{"_i":"frame_0094.jpg","_t":9400,"_vc":99},{"_i":"frame_0096.jpg","_t":9600,"_vc":99},{"_i":"frame_0097.jpg","_t":9700,"_vc":99},{"_i":"frame_0099.jpg","_t":9900,"_vc":99},{"_i":"frame_0100.jpg","_t":10000,"_vc":99},{"_i":"frame_0103.jpg","_t":10300,"_vc":99},{"_i":"frame_0105.jpg","_t":10500,"_vc":99},{"_i":"frame_0106.jpg","_t":10600,"_vc":100}],[{"_i":"frame_0000.jpg","_t":0,"_vc":0},{"_i":"frame_0027.jpg","_t":2700,"_vc":7},{"_i":"frame_0037.jpg","_t":3700,"_vc":22},{"_i":"frame_0043.jpg","_t":4300,"_vc":23},{"_i":"frame_0047.jpg","_t":4700,"_vc":23},{"_i":"frame_0065.jpg","_t":6500,"_vc":44},{"_i":"frame_0069.jpg","_t":6900,"_vc":44},{"_i":"frame_0075.jpg","_t":7500,"_vc":44},{"_i":"frame_0079.jpg","_t":7900,"_vc":89},{"_i":"frame_0084.jpg","_t":8400,"_vc":89},{"_i":"frame_0086.jpg","_t":8600,"_vc":89},{"_i":"frame_0087.jpg","_t":8700,"_vc":89},{"_i":"frame_0089.jpg","_t":8900,"_vc":89},{"_i":"frame_0090.jpg","_t":9000,"_vc":89},{"_i":"frame_0092.jpg","_t":9200,"_vc":89},{"_i":"frame_0094.jpg","_t":9400,"_vc":89},{"_i":"frame_0096.jpg","_t":9600,"_vc":89},{"_i":"frame_0097.jpg","_t":9700,"_vc":89},{"_i":"frame_0100.jpg","_t":10000,"_vc":99},{"_i":"frame_0102.jpg","_t":10200,"_vc":99},{"_i":"frame_0104.jpg","_t":10400,"_vc":99},{"_i":"frame_0106.jpg","_t":10600,"_vc":99},{"_i":"frame_0107.jpg","_t":10700,"_vc":99},{"_i":"frame_0108.jpg","_t":10800,"_vc":99},{"_i":"frame_0110.jpg","_t":11000,"_vc":99},{"_i":"frame_0111.jpg","_t":11100,"_vc":99},{"_i":"frame_0112.jpg","_t":11200,"_vc":99},{"_i":"frame_0114.jpg","_t":11400,"_vc":99},{"_i":"frame_0115.jpg","_t":11500,"_vc":99},{"_i":"frame_0116.jpg","_t":11600,"_vc":100}],[{"_i":"frame_0000.jpg","_t":0,"_vc":0},{"_i":"frame_0027.jpg","_t":2700,"_vc":8},{"_i":"frame_0045.jpg","_t":4500,"_vc":76},{"_i":"frame_0051.jpg","_t":5100,"_vc":76},{"_i":"frame_0070.jpg","_t":7000,"_vc":100},{"_i":"frame_0076.jpg","_t":7600,"_vc":100},{"_i":"frame_0081.jpg","_t":8100,"_vc":99},{"_i":"frame_0088.jpg","_t":8800,"_vc":99},{"_i":"frame_0089.jpg","_t":8900,"_vc":100},{"_i":"frame_0090.jpg","_t":9000,"_vc":100},{"_i":"frame_0092.jpg","_t":9200,"_vc":100},{"_i":"frame_0094.jpg","_t":9400,"_vc":100},{"_i":"frame_0095.jpg","_t":9500,"_vc":100},{"_i":"frame_0096.jpg","_t":9600,"_vc":100},{"_i":"frame_0098.jpg","_t":9800,"_vc":100},{"_i":"frame_0099.jpg","_t":9900,"_vc":100},{"_i":"frame_0100.jpg","_t":10000,"_vc":100},{"_i":"frame_0102.jpg","_t":10200,"_vc":100},{"_i":"frame_0105.jpg","_t":10500,"_vc":99},{"_i":"frame_0106.jpg","_t":10600,"_vc":99},{"_i":"frame_0108.jpg","_t":10800,"_vc":99},{"_i":"frame_0109.jpg","_t":10900,"_vc":99},{"_i":"frame_0110.jpg","_t":11000,"_vc":99},{"_i":"frame_0119.jpg","_t":11900,"_vc":99},{"_i":"frame_0121.jpg","_t":12100,"_vc":99},{"_i":"frame_0123.jpg","_t":12300,"_vc":100}],[{"_i":"frame_0000.jpg","_t":0,"_vc":0},{"_i":"frame_0023.jpg","_t":2300,"_vc":7},{"_i":"frame_0029.jpg","_t":2900,"_vc":22},{"_i":"frame_0039.jpg","_t":3900,"_vc":22},{"_i":"frame_0042.jpg","_t":4200,"_vc":23},{"_i":"frame_0045.jpg","_t":4500,"_vc":23},{"_i":"frame_0046.jpg","_t":4600,"_vc":23},{"_i":"frame_0062.jpg","_t":6200,"_vc":44},{"_i":"frame_0073.jpg","_t":7300,"_vc":44},{"_i":"frame_0078.jpg","_t":7800,"_vc":44},{"_i":"frame_0079.jpg","_t":7900,"_vc":89},{"_i":"frame_0082.jpg","_t":8200,"_vc":89},{"_i":"frame_0083.jpg","_t":8300,"_vc":89},{"_i":"frame_0085.jpg","_t":8500,"_vc":89},{"_i":"frame_0087.jpg","_t":8700,"_vc":89},{"_i":"frame_0088.jpg","_t":8800,"_vc":89},{"_i":"frame_0092.jpg","_t":9200,"_vc":99},{"_i":"frame_0094.jpg","_t":9400,"_vc":100},{"_i":"frame_0095.jpg","_t":9500,"_vc":99},{"_i":"frame_0097.jpg","_t":9700,"_vc":99},{"_i":"frame_0098.jpg","_t":9800,"_vc":99},{"_i":"frame_0099.jpg","_t":9900,"_vc":99},{"_i":"frame_0101.jpg","_t":10100,"_vc":100},{"_i":"frame_0103.jpg","_t":10300,"_vc":99},{"_i":"frame_0104.jpg","_t":10400,"_vc":99},{"_i":"frame_0106.jpg","_t":10600,"_vc":99},{"_i":"frame_0108.jpg","_t":10800,"_vc":99},{"_i":"frame_0109.jpg","_t":10900,"_vc":100}],[{"_i":"frame_0000.jpg","_t":0,"_vc":0},{"_i":"frame_0020.jpg","_t":2000,"_vc":7},{"_i":"frame_0027.jpg","_t":2700,"_vc":22},{"_i":"frame_0035.jpg","_t":3500,"_vc":22},{"_i":"frame_0042.jpg","_t":4200,"_vc":23},{"_i":"frame_0046.jpg","_t":4600,"_vc":23},{"_i":"frame_0064.jpg","_t":6400,"_vc":44},{"_i":"frame_0070.jpg","_t":7000,"_vc":44},{"_i":"frame_0077.jpg","_t":7700,"_vc":44},{"_i":"frame_0080.jpg","_t":8000,"_vc":89},{"_i":"frame_0082.jpg","_t":8200,"_vc":89},{"_i":"frame_0084.jpg","_t":8400,"_vc":89},{"_i":"frame_0086.jpg","_t":8600,"_vc":89},{"_i":"frame_0089.jpg","_t":8900,"_vc":89},{"_i":"frame_0092.jpg","_t":9200,"_vc":99},{"_i":"frame_0094.jpg","_t":9400,"_vc":99},{"_i":"frame_0096.jpg","_t":9600,"_vc":99},{"_i":"frame_0097.jpg","_t":9700,"_vc":99},{"_i":"frame_0099.jpg","_t":9900,"_vc":99},{"_i":"frame_0100.jpg","_t":10000,"_vc":99},{"_i":"frame_0102.jpg","_t":10200,"_vc":99},{"_i":"frame_0103.jpg","_t":10300,"_vc":99},{"_i":"frame_0104.jpg","_t":10400,"_vc":99},{"_i":"frame_0106.jpg","_t":10600,"_vc":99},{"_i":"frame_0107.jpg","_t":10700,"_vc":99},{"_i":"frame_0108.jpg","_t":10800,"_vc":99},{"_i":"frame_0109.jpg","_t":10900,"_vc":100}],[{"_i":"frame_0000.jpg","_t":0,"_vc":0},{"_i":"frame_0020.jpg","_t":2000,"_vc":13},{"_i":"frame_0023.jpg","_t":2300,"_vc":75},{"_i":"frame_0031.jpg","_t":3100,"_vc":75},{"_i":"frame_0042.jpg","_t":4200,"_vc":75},{"_i":"frame_0051.jpg","_t":5100,"_vc":76},{"_i":"frame_0075.jpg","_t":7500,"_vc":99},{"_i":"frame_0077.jpg","_t":7700,"_vc":100},{"_i":"frame_0082.jpg","_t":8200,"_vc":99},{"_i":"frame_0083.jpg","_t":8300,"_vc":100},{"_i":"frame_0085.jpg","_t":8500,"_vc":99},{"_i":"frame_0087.jpg","_t":8700,"_vc":99},{"_i":"frame_0089.jpg","_t":8900,"_vc":99},{"_i":"frame_0091.jpg","_t":9100,"_vc":99},{"_i":"frame_0092.jpg","_t":9200,"_vc":99},{"_i":"frame_0094.jpg","_t":9400,"_vc":99},{"_i":"frame_0095.jpg","_t":9500,"_vc":99},{"_i":"frame_0097.jpg","_t":9700,"_vc":99},{"_i":"frame_0099.jpg","_t":9900,"_vc":99},{"_i":"frame_0102.jpg","_t":10200,"_vc":99},{"_i":"frame_0104.jpg","_t":10400,"_vc":99},{"_i":"frame_0105.jpg","_t":10500,"_vc":99},{"_i":"frame_0106.jpg","_t":10600,"_vc":99},{"_i":"frame_0108.jpg","_t":10800,"_vc":100}],[{"_i":"frame_0000.jpg","_t":0,"_vc":0},{"_i":"frame_0028.jpg","_t":2800,"_vc":75},{"_i":"frame_0033.jpg","_t":3300,"_vc":75},{"_i":"frame_0039.jpg","_t":3900,"_vc":75},{"_i":"frame_0047.jpg","_t":4700,"_vc":75},{"_i":"frame_0068.jpg","_t":6800,"_vc":92},{"_i":"frame_0072.jpg","_t":7200,"_vc":92},{"_i":"frame_0076.jpg","_t":7600,"_vc":92},{"_i":"frame_0078.jpg","_t":7800,"_vc":92},{"_i":"frame_0081.jpg","_t":8100,"_vc":100},{"_i":"frame_0083.jpg","_t":8300,"_vc":100},{"_i":"frame_0090.jpg","_t":9000,"_vc":99},{"_i":"frame_0093.jpg","_t":9300,"_vc":99},{"_i":"frame_0095.jpg","_t":9500,"_vc":99},{"_i":"frame_0096.jpg","_t":9600,"_vc":99},{"_i":"frame_0098.jpg","_t":9800,"_vc":99},{"_i":"frame_0099.jpg","_t":9900,"_vc":99},{"_i":"frame_0101.jpg","_t":10100,"_vc":99},{"_i":"frame_0102.jpg","_t":10200,"_vc":99},{"_i":"frame_0104.jpg","_t":10400,"_vc":99},{"_i":"frame_0106.jpg","_t":10600,"_vc":99},{"_i":"frame_0108.jpg","_t":10800,"_vc":99},{"_i":"frame_0109.jpg","_t":10900,"_vc":99},{"_i":"frame_0110.jpg","_t":11000,"_vc":99},{"_i":"frame_0112.jpg","_t":11200,"_vc":99},{"_i":"frame_0114.jpg","_t":11400,"_vc":100}]],"visualComplete":[10600,11600,7000,9400,10900,7700,8100],"lighthouse":[null,null,null,null,null,null,null],"pagespeed":[84,84,84,85,83,84,84]}}