{"_ts":[1567328672],"_r":{"breakdown":{"html":{"bytes":[31176],"requests":[16]},"js":{"bytes":[507966],"requests":[25]},"css":{"bytes":[60126],"requests":[2]},"image":{"bytes":[353260],"requests":[30]},"flash":{"bytes":[0],"requests":[0]},"font":{"bytes":[634592],"requests":[25]},"video":{"bytes":[0],"requests":[0]},"other":{"bytes":[1770],"requests":[8]}},"date":[1567328672],"domElements":[1653],"domInteractive":[2289],"firstPaint":[2057.0249999946],"fullyLoaded":[10938],"id":["190901_C4_eff9f1dc81165202368f879ef1a31700"],"loadTime":[8115],"render":[2100],"SpeedIndex":[2359],"TTFB":[742],"videoFrames":[[{"_i":"ms_000000.jpg","_t":0,"_vc":0},{"_i":"ms_002100.jpg","_t":2100,"_vc":84},{"_i":"ms_002200.jpg","_t":2200,"_vc":89},{"_i":"ms_002300.jpg","_t":2300,"_vc":90},{"_i":"ms_002600.jpg","_t":2600,"_vc":94},{"_i":"ms_002900.jpg","_t":2900,"_vc":94},{"_i":"ms_003100.jpg","_t":3100,"_vc":94},{"_i":"ms_003200.jpg","_t":3200,"_vc":94},{"_i":"ms_003300.jpg","_t":3300,"_vc":94},{"_i":"ms_005300.jpg","_t":5300,"_vc":94},{"_i":"ms_005800.jpg","_t":5800,"_vc":98},{"_i":"ms_006300.jpg","_t":6300,"_vc":100}]],"visualComplete":[6300],"lighthouse":[35],"pagespeed":[83]}}