{"_ts":[1551468083],"_r":{"breakdown":{"html":{"bytes":[45195],"requests":[27]},"js":{"bytes":[474247],"requests":[24]},"css":{"bytes":[76533],"requests":[3]},"image":{"bytes":[190141],"requests":[33]},"flash":{"bytes":[0],"requests":[0]},"font":{"bytes":[634592],"requests":[25]},"video":{"bytes":[0],"requests":[0]},"other":{"bytes":[7640],"requests":[13]}},"date":[1551468083],"domElements":[2152],"domInteractive":[3766],"firstPaint":[2681.1799999996],"fullyLoaded":[17354],"id":["190301_1G_ca8be3969e3856c3c15a3e3450fdd7d1"],"loadTime":[15075],"render":[3100],"SpeedIndex":[4719],"TTFB":[475],"videoFrames":[[{"_i":"ms_000000.jpg","_t":0,"_vc":0},{"_i":"ms_003100.jpg","_t":3100,"_vc":85},{"_i":"ms_005200.jpg","_t":5200,"_vc":86},{"_i":"ms_010400.jpg","_t":10400,"_vc":91},{"_i":"ms_016800.jpg","_t":16800,"_vc":100}]],"visualComplete":[16800],"lighthouse":[35],"pagespeed":[83]}}