{"_ts":[1517563687,1517648763,1517735349,1517821462,1517907950,1518130255,1518223381],"_r":{"breakdown":{"html":{"bytes":[62795,63659,63747,64449,63758,97653,97598],"requests":[20,21,21,22,21,21,21]},"js":{"bytes":[357845,372700,371710,368176,369790,706586,769728],"requests":[17,17,17,17,17,19,19]},"css":{"bytes":[57724,57749,65561,65561,73899,80100,91470],"requests":[3,3,3,3,3,3,3]},"image":{"bytes":[725453,745473,756480,747914,740841,1122280,1095645],"requests":[31,31,31,31,30,30,30]},"flash":{"bytes":[0,0,0,0,0,0,0],"requests":[0,0,0,0,0,0,0]},"font":{"bytes":[198536,204921,195097,202763,198382,1307285,1307302],"requests":[12,12,12,12,12,45,45]},"video":{"bytes":[0,0,0,0,0,0,0],"requests":[0,0,0,0,0,0,0]},"other":{"bytes":[1306,1295,1266,1311,1306,8333,6895],"requests":[6,6,5,6,6,6,5]}},"date":[1517563687,1517648763,1517735349,1517821462,1517907950,1518130255,1518223381],"domElements":[2002,1996,1999,2000,1989,1990,1990],"domInteractive":[2723,2977,2767,2763,2750,4494,3597],"firstPaint":[1940,2141,1871,1736,1902,3216.7999999947,2426.6000000061],"fullyLoaded":[10625,11078,9737,10805,10112,14431,14209],"id":["180202_98_99121f73a7781234f0c7ac9946b00d67","180203_P7_02dc6bd9928a0035c20233f02015d373","180204_4W_e6a49146251e8c4a46bff3090fe79f17","180205_M4_653b74dba142e66244c0193efa39778b","180206_RV_75e6c54c00a53d8e2133fb166d3604c3","180208_2Y_5f42f96ff084148ca1ab72fc4516c122","180209_Y0_a8ac0752d0e93bd6e608fa3db4a197a8"],"loadTime":[2903,3426,2615,3078,2798,4705,3884],"render":[1898,1903,1695,1566,1703,3333,2600],"SpeedIndex":[3819,4078,3452,3631,2447,4526,3579],"TTFB":[457,394,469,267,400,1683,649],"videoFrames":[[{"_i":"frame_0000.jpg","_t":0,"_vc":0},{"_i":"frame_0019.jpg","_t":1900,"_vc":26},{"_i":"frame_0021.jpg","_t":2100,"_vc":79},{"_i":"frame_0028.jpg","_t":2800,"_vc":79},{"_i":"frame_0034.jpg","_t":3400,"_vc":79},{"_i":"frame_0044.jpg","_t":4400,"_vc":79},{"_i":"frame_0064.jpg","_t":6400,"_vc":79},{"_i":"frame_0071.jpg","_t":7100,"_vc":79},{"_i":"frame_0078.jpg","_t":7800,"_vc":79},{"_i":"frame_0095.jpg","_t":9500,"_vc":79},{"_i":"frame_0096.jpg","_t":9600,"_vc":80},{"_i":"frame_0097.jpg","_t":9700,"_vc":80},{"_i":"frame_0101.jpg","_t":10100,"_vc":80},{"_i":"frame_0102.jpg","_t":10200,"_vc":86},{"_i":"frame_0106.jpg","_t":10600,"_vc":99},{"_i":"frame_0108.jpg","_t":10800,"_vc":99},{"_i":"frame_0110.jpg","_t":11000,"_vc":99},{"_i":"frame_0111.jpg","_t":11100,"_vc":99},{"_i":"frame_0113.jpg","_t":11300,"_vc":99},{"_i":"frame_0114.jpg","_t":11400,"_vc":99},{"_i":"frame_0116.jpg","_t":11600,"_vc":99},{"_i":"frame_0118.jpg","_t":11800,"_vc":99},{"_i":"frame_0120.jpg","_t":12000,"_vc":99},{"_i":"frame_0122.jpg","_t":12200,"_vc":99},{"_i":"frame_0123.jpg","_t":12300,"_vc":99},{"_i":"frame_0125.jpg","_t":12500,"_vc":99},{"_i":"frame_0126.jpg","_t":12600,"_vc":100}],[{"_i":"frame_0000.jpg","_t":0,"_vc":0},{"_i":"frame_0019.jpg","_t":1900,"_vc":50},{"_i":"frame_0026.jpg","_t":2600,"_vc":78},{"_i":"frame_0030.jpg","_t":3000,"_vc":78},{"_i":"frame_0039.jpg","_t":3900,"_vc":78},{"_i":"frame_0043.jpg","_t":4300,"_vc":78},{"_i":"frame_0051.jpg","_t":5100,"_vc":79},{"_i":"frame_0098.jpg","_t":9800,"_vc":79},{"_i":"frame_0106.jpg","_t":10600,"_vc":79},{"_i":"frame_0111.jpg","_t":11100,"_vc":99},{"_i":"frame_0113.jpg","_t":11300,"_vc":99},{"_i":"frame_0114.jpg","_t":11400,"_vc":99},{"_i":"frame_0116.jpg","_t":11600,"_vc":99},{"_i":"frame_0118.jpg","_t":11800,"_vc":99},{"_i":"frame_0120.jpg","_t":12000,"_vc":99},{"_i":"frame_0121.jpg","_t":12100,"_vc":99},{"_i":"frame_0122.jpg","_t":12200,"_vc":99},{"_i":"frame_0123.jpg","_t":12300,"_vc":99},{"_i":"frame_0124.jpg","_t":12400,"_vc":99},{"_i":"frame_0126.jpg","_t":12600,"_vc":99},{"_i":"frame_0128.jpg","_t":12800,"_vc":99},{"_i":"frame_0129.jpg","_t":12900,"_vc":100},{"_i":"frame_0130.jpg","_t":13000,"_vc":100}],[{"_i":"frame_0000.jpg","_t":0,"_vc":0},{"_i":"frame_0017.jpg","_t":1700,"_vc":41},{"_i":"frame_0019.jpg","_t":1900,"_vc":79},{"_i":"frame_0021.jpg","_t":2100,"_vc":79},{"_i":"frame_0033.jpg","_t":3300,"_vc":79},{"_i":"frame_0044.jpg","_t":4400,"_vc":79},{"_i":"frame_0048.jpg","_t":4800,"_vc":79},{"_i":"frame_0067.jpg","_t":6700,"_vc":79},{"_i":"frame_0076.jpg","_t":7600,"_vc":79},{"_i":"frame_0085.jpg","_t":8500,"_vc":80},{"_i":"frame_0090.jpg","_t":9000,"_vc":80},{"_i":"frame_0093.jpg","_t":9300,"_vc":80},{"_i":"frame_0097.jpg","_t":9700,"_vc":99},{"_i":"frame_0099.jpg","_t":9900,"_vc":99},{"_i":"frame_0102.jpg","_t":10200,"_vc":99},{"_i":"frame_0104.jpg","_t":10400,"_vc":99},{"_i":"frame_0105.jpg","_t":10500,"_vc":100},{"_i":"frame_0114.jpg","_t":11400,"_vc":100},{"_i":"frame_0116.jpg","_t":11600,"_vc":100},{"_i":"frame_0117.jpg","_t":11700,"_vc":100}],[{"_i":"frame_0000.jpg","_t":0,"_vc":0},{"_i":"frame_0016.jpg","_t":1600,"_vc":27},{"_i":"frame_0018.jpg","_t":1800,"_vc":79},{"_i":"frame_0020.jpg","_t":2000,"_vc":79},{"_i":"frame_0021.jpg","_t":2100,"_vc":79},{"_i":"frame_0034.jpg","_t":3400,"_vc":79},{"_i":"frame_0039.jpg","_t":3900,"_vc":79},{"_i":"frame_0045.jpg","_t":4500,"_vc":79},{"_i":"frame_0048.jpg","_t":4800,"_vc":79},{"_i":"frame_0080.jpg","_t":8000,"_vc":79},{"_i":"frame_0087.jpg","_t":8700,"_vc":80},{"_i":"frame_0099.jpg","_t":9900,"_vc":80},{"_i":"frame_0103.jpg","_t":10300,"_vc":86},{"_i":"frame_0110.jpg","_t":11000,"_vc":99},{"_i":"frame_0111.jpg","_t":11100,"_vc":99},{"_i":"frame_0113.jpg","_t":11300,"_vc":99},{"_i":"frame_0115.jpg","_t":11500,"_vc":99},{"_i":"frame_0117.jpg","_t":11700,"_vc":99},{"_i":"frame_0118.jpg","_t":11800,"_vc":99},{"_i":"frame_0119.jpg","_t":11900,"_vc":99},{"_i":"frame_0121.jpg","_t":12100,"_vc":99},{"_i":"frame_0123.jpg","_t":12300,"_vc":99},{"_i":"frame_0125.jpg","_t":12500,"_vc":99},{"_i":"frame_0127.jpg","_t":12700,"_vc":99},{"_i":"frame_0128.jpg","_t":12800,"_vc":100}],[{"_i":"frame_0000.jpg","_t":0,"_vc":0},{"_i":"frame_0017.jpg","_t":1700,"_vc":65},{"_i":"frame_0021.jpg","_t":2100,"_vc":92},{"_i":"frame_0034.jpg","_t":3400,"_vc":92},{"_i":"frame_0037.jpg","_t":3700,"_vc":92},{"_i":"frame_0043.jpg","_t":4300,"_vc":93},{"_i":"frame_0048.jpg","_t":4800,"_vc":93},{"_i":"frame_0085.jpg","_t":8500,"_vc":93},{"_i":"frame_0087.jpg","_t":8700,"_vc":92},{"_i":"frame_0092.jpg","_t":9200,"_vc":93},{"_i":"frame_0093.jpg","_t":9300,"_vc":93},{"_i":"frame_0095.jpg","_t":9500,"_vc":93},{"_i":"frame_0099.jpg","_t":9900,"_vc":93},{"_i":"frame_0101.jpg","_t":10100,"_vc":99},{"_i":"frame_0107.jpg","_t":10700,"_vc":99},{"_i":"frame_0109.jpg","_t":10900,"_vc":99},{"_i":"frame_0111.jpg","_t":11100,"_vc":99},{"_i":"frame_0113.jpg","_t":11300,"_vc":99},{"_i":"frame_0115.jpg","_t":11500,"_vc":99},{"_i":"frame_0117.jpg","_t":11700,"_vc":99},{"_i":"frame_0119.jpg","_t":11900,"_vc":99},{"_i":"frame_0121.jpg","_t":12100,"_vc":100}],[{"_i":"ms_000000.jpg","_t":0,"_vc":0},{"_i":"ms_003333.jpg","_t":3333,"_vc":40},{"_i":"ms_004033.jpg","_t":4033,"_vc":93},{"_i":"ms_004867.jpg","_t":4867,"_vc":93},{"_i":"ms_007267.jpg","_t":7267,"_vc":95},{"_i":"ms_008800.jpg","_t":8800,"_vc":93},{"_i":"ms_011700.jpg","_t":11700,"_vc":93},{"_i":"ms_014267.jpg","_t":14267,"_vc":94},{"_i":"ms_015733.jpg","_t":15733,"_vc":100},{"_i":"ms_016567.jpg","_t":16567,"_vc":100},{"_i":"ms_016833.jpg","_t":16833,"_vc":100},{"_i":"ms_016867.jpg","_t":16867,"_vc":100},{"_i":"ms_017000.jpg","_t":17000,"_vc":100},{"_i":"ms_017067.jpg","_t":17067,"_vc":100},{"_i":"ms_017167.jpg","_t":17167,"_vc":100}],[{"_i":"ms_000000.jpg","_t":0,"_vc":0},{"_i":"ms_002600.jpg","_t":2600,"_vc":68},{"_i":"ms_003167.jpg","_t":3167,"_vc":94},{"_i":"ms_003800.jpg","_t":3800,"_vc":94},{"_i":"ms_005000.jpg","_t":5000,"_vc":93},{"_i":"ms_006734.jpg","_t":6734,"_vc":93},{"_i":"ms_013167.jpg","_t":13167,"_vc":94},{"_i":"ms_015100.jpg","_t":15100,"_vc":100},{"_i":"ms_015834.jpg","_t":15834,"_vc":100},{"_i":"ms_016167.jpg","_t":16167,"_vc":100},{"_i":"ms_016300.jpg","_t":16300,"_vc":100},{"_i":"ms_016367.jpg","_t":16367,"_vc":100},{"_i":"ms_016567.jpg","_t":16567,"_vc":100}]],"visualComplete":[12600,12900,10500,12800,12100,15733,15100],"lighthouse":[null,null,null,null,null,null,null],"pagespeed":[80,80,80,80,81,80,81]}}