{"_ts":[1500289046],"_r":{"breakdown":{"html":{"bytes":[70979],"requests":[7]},"js":{"bytes":[472093],"requests":[13]},"css":{"bytes":[50978],"requests":[3]},"image":{"bytes":[2751555],"requests":[44]},"flash":{"bytes":[0],"requests":[0]},"font":{"bytes":[139175],"requests":[6]},"other":{"bytes":[1409],"requests":[4]}},"date":[1500289046],"domElements":[1477],"domInteractive":[3185],"firstPaint":[1894],"fullyLoaded":[8578],"id":["170717_BX_PAY"],"loadTime":[7906],"render":[2471],"SpeedIndex":[3543],"TTFB":[739],"videoFrames":[[{"_i":"frame_0000.jpg","_t":0,"_vc":0},{"_i":"frame_0025.jpg","_t":2500,"_vc":2},{"_i":"frame_0027.jpg","_t":2700,"_vc":3},{"_i":"frame_0034.jpg","_t":3400,"_vc":18},{"_i":"frame_0036.jpg","_t":3600,"_vc":99},{"_i":"frame_0040.jpg","_t":4000,"_vc":100},{"_i":"frame_0087.jpg","_t":8700,"_vc":100}]],"visualComplete":[4000],"lighthouse":[null],"pagespeed":[41]}}